Workbook

Sheet ビジョン・戦略
B2: 本気でカードで儲ける トレーディングカードショップ 事業ビジョン
B3: KGI：月次営業利益200万円 ｜ ポケモン・ワンピース主軸 ｜ 2026年7月スタート
B5: 🎯 ミッション ／ ビジョン
B6: ミッション | C6: 「カードに本気な人と、カードを楽しみたい人を、最高の体験でつなぐ」 買取・販売・イベントを通じて、地域とオンラインの両方でカルチャーの拠点となる。
B7: ビジョン | C7: 3年以内に年商3億・月次利益500万円を達成し、直営2店舗＋EC年商1億の 「ポケモン×ワンピース専門ショップ」としてブランド確立を目指す。
B9: 💴 収益モデル 「月次売上1,000万・営業利益200万」の構造
B10: 新品販売（ECメイン） | C10: 売上700万 / 原価率70% / 粗利210万 ← ボックス・パック・シングル。 メルカリShops・自社EC・実店舗の3チャネル展開で在庫回転率を最大化。
B11: 中古・シングル買取販売 | C11: 売上300万 / 原価率50% / 粗利150万 ← 個人買取が最大の利益源。 「その場で査定・即現金」を武器に買取量を積み上げ、粗利50%以上を死守する。
B12: 販管費コントロール | C12: 月次販管費160万以内に抑制。人件費・家賃・広告の3大費目を毎月モニタリング。 EC手数料はチャネルミックスで実質2%未満に最適化する。
B13: スケール戦略 | C13: 達成後は中古買取強化（粗利率が高い）・イベント主催（原価ほぼゼロ）・ サブスク封入パック等で高粗利の売上ミックスを改善し営業利益率を30%以上へ。
B15: 📊 月次KPI ターゲット（200万利益達成ライン）
B16: 月次売上目標 | C16: 1,000万円（新品700万＋中古300万）
B17: 月次粗利目標 | C17: 360万円（粗利率36%）
B18: 月次販管費上限 | C18: 160万円（粗利の44%以内）
B19: 月次営業利益目標 | C19: 200万円（利益率20%） ★KGI
B20: 新品在庫回転率 | C20: 月2.5回転以上（適正在庫: 280万円規模）
B21: 中古買取件数 | C21: 月80件以上（平均単価3.75万円/件）
B22: EC売上比率 | C22: 新品の50%以上はEC経由（送料・手数料コスト最適化）
B23: SNSフォロワー | C23: 開店6ヶ月でInstagram/X 合計5,000人以上
B25: 🗺️ 成長ロードマップ
B26: Phase 1 立上期 （〜3ヶ月） | C26: 【仕込み】在庫確保・EC出品体制構築・SNSアカウント開設。 買取ルート開拓（個人・カードショップ・オークション）。売上500万→700万ランプアップ。
B27: Phase 2 安定期 （4〜9ヶ月） | C27: 【稼ぐ】月次売上1,000万・利益200万の安定達成。 リピーター育成・メルマガ・LINE公式アカウントで顧客ロイヤルティ強化。
B28: Phase 3 拡張期 （10〜13ヶ月） | C28: 【攻める】大型イベント主催（トーナメント等）・限定BOX予約販売導入。 利益の一部を2号店の保証金・初期在庫に積立開始。目標: 累計利益2,500万円突破。
B29: Phase 4 スケール （2年目〜） | C29: 【広げる】直営2店舗目 or フランチャイズ展開・法人化・外部資本調達検討。 年商3億・月次利益500万円達成で「業界標準の独立カードショップ」モデルを確立。
B31: ⚡ 絶対に外せない勝ち筋 3原則
B32: 原則① 買取が命 | C32: 「売る前に買う」。高粗利の中古シングルを安定調達できれば利益は安定する。 買取価格の査定精度を上げ、他店より1〜5%高く買って、2〜3倍で売る構造を作る。
B33: 原則② 在庫を腐らせない | C33: 新品は「封入期待値×市場相場」を毎日ウォッチし、需要ピーク前に仕入れ、ピークで売り切る。 売れ残りは即EC値引き・抱き合わせ販売で現金化。在庫は「死に金」と心得る。
B34: 原則③ 数字で経営する | C34: このPLを毎月更新し、粗利率・営業利益・在庫回転率の3指標を週次でチェック。 「なんとなく売れてる」ではなく「なぜ儲かったか/損したか」を数字で語れる経営者になる。

Sheet 月次PL
B2: 月次PLシミュレーション 「月次営業利益200万円」達成プラン
B3: 期間：2026年7月〜2027年7月（13ヶ月） ｜ 売上1,000万 / 粗利360万 / 販管費160万 / 営業利益200万 ｜ 単位：円
B5: 項 目 | C5: 2026年7月 | D5: 2026年8月 | E5: 2026年9月 | F5: 2026年10月 | G5: 2026年11月 | H5: 2026年12月 | I5: 2027年1月 | J5: 2027年2月 | K5: 2027年3月 | L5: 2027年4月 | M5: 2027年5月 | N5: 2027年6月 | O5: 2027年7月 | P5: 年間合計
B6: ▌ 売上高
B7: 新品売上 | C7: 7000000 | D7: 7000000 | E7: 7000000 | F7: 7000000 | G7: 7000000 | H7: 7000000 | I7: 7000000 | J7: 7000000 | K7: 7000000 | L7: 7000000 | M7: 7000000 | N7: 7000000 | O7: 7000000 | P7: =SUM(C7:O7)
B8: 中古売上 | C8: 3000000 | D8: 3000000 | E8: 3000000 | F8: 3000000 | G8: 3000000 | H8: 3000000 | I8: 3000000 | J8: 3000000 | K8: 3000000 | L8: 3000000 | M8: 3000000 | N8: 3000000 | O8: 3000000 | P8: =SUM(C8:O8)
B9: 売上合計 | C9: =C7+C8 | D9: =D7+D8 | E9: =E7+E8 | F9: =F7+F8 | G9: =G7+G8 | H9: =H7+H8 | I9: =I7+I8 | J9: =J7+J8 | ... O9: =O7+O8 | P9: =SUM(C9:O9)
B11: ▌ 売上原価
B12: 新品原価（原価率70%） | C12: =ROUND(C7*0.7,0) | D12: =ROUND(D7*0.7,0) | E12: =ROUND(E7*0.7,0) | F12: =ROUND(F7*0.7,0) | G12: =ROUND(G7*0.7,0) | H12: =ROUND(H7*0.7,0) | I12: =ROUND(I7*0.7,0) | J12: =ROUND(J7*0.7,0) | ... O12: =ROUND(O7*0.7,0) | P12: =SUM(C12:O12)
B13: 中古原価（原価率50%） | C13: =ROUND(C8*0.5,0) | D13: =ROUND(D8*0.5,0) | E13: =ROUND(E8*0.5,0) | F13: =ROUND(F8*0.5,0) | G13: =ROUND(G8*0.5,0) | H13: =ROUND(H8*0.5,0) | I13: =ROUND(I8*0.5,0) | J13: =ROUND(J8*0.5,0) | ... O13: =ROUND(O8*0.5,0) | P13: =SUM(C13:O13)
B14: 原価合計 | C14: =C12+C13 | D14: =D12+D13 | E14: =E12+E13 | F14: =F12+F13 | G14: =G12+G13 | H14: =H12+H13 | I14: =I12+I13 | J14: =J12+J13 | ... O14: =O12+O13 | P14: =SUM(C14:O14)
B16: ▌ 売上総利益（粗利） 目標：360万円/月 | C16: =C9-C14 | D16: =D9-D14 | E16: =E9-E14 | F16: =F9-F14 | G16: =G9-G14 | H16: =H9-H14 | I16: =I9-I14 | J16: =J9-J14 | ... O16: =O9-O14 | P16: =SUM(C16:O16)
B18: ▌ 販売管理費 ※詳細内訳は「販管費内訳」シート参照
B19: 地代家賃 | C19: ='販管費内訳'!D8 | D19: ='販管費内訳'!E8 | E19: ='販管費内訳'!F8 | F19: ='販管費内訳'!G8 | G19: ='販管費内訳'!H8 | H19: ='販管費内訳'!I8 | I19: ='販管費内訳'!J8 | J19: ='販管費内訳'!K8 | ... O19: ='販管費内訳'!P8 | P19: =SUM(C19:O19)
B20: 人件費（正社員） | C20: ='販管費内訳'!D14 | D20: ='販管費内訳'!E14 | E20: ='販管費内訳'!F14 | F20: ='販管費内訳'!G14 | G20: ='販管費内訳'!H14 | H20: ='販管費内訳'!I14 | I20: ='販管費内訳'!J14 | J20: ='販管費内訳'!K14 | ... O20: ='販管費内訳'!P14 | P20: =SUM(C20:O20)
B21: 人件費（アルバイト） | C21: ='販管費内訳'!D19 | D21: ='販管費内訳'!E19 | E21: ='販管費内訳'!F19 | F21: ='販管費内訳'!G19 | G21: ='販管費内訳'!H19 | H21: ='販管費内訳'!I19 | I21: ='販管費内訳'!J19 | J21: ='販管費内訳'!K19 | ... O21: ='販管費内訳'!P19 | P21: =SUM(C21:O21)
B22: 広告宣伝費・イベント費 | C22: ='販管費内訳'!D25 | D22: ='販管費内訳'!E25 | E22: ='販管費内訳'!F25 | F22: ='販管費内訳'!G25 | G22: ='販管費内訳'!H25 | H22: ='販管費内訳'!I25 | I22: ='販管費内訳'!J25 | J22: ='販管費内訳'!K25 | ... O22: ='販管費内訳'!P25 | P22: =SUM(C22:O22)
B23: EC決済手数料 | C23: ='販管費内訳'!D30 | D23: ='販管費内訳'!E30 | E23: ='販管費内訳'!F30 | F23: ='販管費内訳'!G30 | G23: ='販管費内訳'!H30 | H23: ='販管費内訳'!I30 | I23: ='販管費内訳'!J30 | J23: ='販管費内訳'!K30 | ... O23: ='販管費内訳'!P30 | P23: =SUM(C23:O23)
B24: 荷造運賃 | C24: ='販管費内訳'!D35 | D24: ='販管費内訳'!E35 | E24: ='販管費内訳'!F35 | F24: ='販管費内訳'!G35 | G24: ='販管費内訳'!H35 | H24: ='販管費内訳'!I35 | I24: ='販管費内訳'!J35 | J24: ='販管費内訳'!K35 | ... O24: ='販管費内訳'!P35 | P24: =SUM(C24:O24)
B25: 水道光熱費・システム・その他 | C25: ='販管費内訳'!D43 | D25: ='販管費内訳'!E43 | E25: ='販管費内訳'!F43 | F25: ='販管費内訳'!G43 | G25: ='販管費内訳'!H43 | H25: ='販管費内訳'!I43 | I25: ='販管費内訳'!J43 | J25: ='販管費内訳'!K43 | ... O25: ='販管費内訳'!P43 | P25: =SUM(C25:O25)
B26: 販管費合計 | C26: =C19+C20+C21+C22+C23+C24+C25 | D26: =D19+D20+D21+D22+D23+D24+D25 | E26: =E19+E20+E21+E22+E23+E24+E25 | F26: =F19+F20+F21+F22+F23+F24+F25 | G26: =G19+G20+G21+G22+G23+G24+G25 | H26: =H19+H20+H21+H22+H23+H24+H25 | I26: =I19+I20+I21+I22+I23+I24+I25 | J26: =J19+J20+J21+J22+J23+J24+J25 | ... O26: =O19+O20+O21+O22+O23+O24+O25 | P26: =SUM(C26:O26)
B28: ▌ 営業利益 ★目標：200万円/月 | C28: =C16-C26 | D28: =D16-D26 | E28: =E16-E26 | F28: =F16-F26 | G28: =G16-G26 | H28: =H16-H26 | I28: =I16-I26 | J28: =J16-J26 | ... O28: =O16-O26 | P28: =SUM(C28:O28)
B30: 粗利率（%） | C30: =IFERROR(C16/C9*100,0) | D30: =IFERROR(D16/D9*100,0) | E30: =IFERROR(E16/E9*100,0) | F30: =IFERROR(F16/F9*100,0) | G30: =IFERROR(G16/G9*100,0) | H30: =IFERROR(H16/H9*100,0) | I30: =IFERROR(I16/I9*100,0) | J30: =IFERROR(J16/J9*100,0) | ... P30: =IFERROR(P16/P9*100,0)
B31: 営業利益率（%） | C31: =IFERROR(C28/C9*100,0) | D31: =IFERROR(D28/D9*100,0) | E31: =IFERROR(E28/E9*100,0) | F31: =IFERROR(F28/F9*100,0) | G31: =IFERROR(G28/G9*100,0) | H31: =IFERROR(H28/H9*100,0) | I31: =IFERROR(I28/I9*100,0) | J31: =IFERROR(J28/J9*100,0) | ... P31: =IFERROR(P28/P9*100,0)

Sheet 販管費内訳
B2: 販管費内訳 詳細シート
B3: 各費目の内訳を入力 → PLシートの合計行に自動反映 ｜ 単位：円
B5: 費目（内訳） | C5: PL科目 | D5: 2026年7月 | E5: 2026年8月 | F5: 2026年9月 | G5: 2026年10月 | H5: 2026年11月 | I5: 2026年12月 | J5: 2027年1月 | K5: 2027年2月 | L5: 2027年3月 | M5: 2027年4月 | N5: 2027年5月 | O5: 2027年6月 | P5: 2027年7月 | Q5: 年間合計
B6: ▌ 地代家賃
B7: 倉庫賃料 | D7: 50000 | E7: 50000 | F7: 50000 | G7: 50000 | H7: 50000 | I7: 50000 | J7: 50000 | K7: 50000 | L7: 50000 | M7: 50000 | N7: 50000 | O7: 50000 | P7: 50000 | Q7: =SUM(D7:P7)
B8: 地代家賃 計 ← PLシートの「地代家賃」に連動 | C8: 地代家賃 | D8: =D7+D7 | E8: =E7+E7 | F8: =F7+F7 | G8: =G7+G7 | H8: =H7+H7 | I8: =I7+I7 | J8: =J7+J7 | K8: =K7+K7 | ... P8: =P7+P7 | Q8: =SUM(D8:P8)
B10: ▌ 人件費（正社員）
B11: 正社員① 基本給 | D11: 400000 | E11: 400000 | F11: 400000 | G11: 400000 | H11: 400000 | I11: 400000 | J11: 400000 | K11: 400000 | L11: 400000 | M11: 400000 | N11: 400000 | O11: 400000 | P11: 400000 | Q11: =SUM(D11:P11)
B12: 正社員② 基本給 | D12: 250000 | E12: 250000 | F12: 250000 | G12: 250000 | H12: 250000 | I12: 250000 | J12: 250000 | K12: 250000 | L12: 250000 | M12: 250000 | N12: 250000 | O12: 250000 | P12: 250000 | Q12: =SUM(D12:P12)
B13: 社会保険料（会社負担） | D13: 110000 | E13: 110000 | F13: 110000 | G13: 110000 | H13: 110000 | I13: 110000 | J13: 110000 | K13: 110000 | L13: 110000 | M13: 110000 | N13: 110000 | O13: 110000 | P13: 110000 | Q13: =SUM(D13:P13)
B14: 人件費（正社員） 計 ← PLシートの「人件費（正社員）」に連動 | C14: 人件費（正社員） | D14: =D11+D12+D13 | E14: =E11+E12+E13 | F14: =F11+F12+F13 | G14: =G11+G12+G13 | H14: =H11+H12+H13 | I14: =I11+I12+I13 | J14: =J11+J12+J13 | K14: =K11+K12+K13 | ... P14: =P11+P12+P13 | Q14: =SUM(D14:P14)
B16: ▌ 人件費（アルバイト）
B17: アルバイト賃金 | D17: 130000 | E17: 130000 | F17: 130000 | G17: 130000 | H17: 130000 | I17: 130000 | J17: 130000 | K17: 130000 | L17: 130000 | M17: 130000 | N17: 130000 | O17: 130000 | P17: 130000 | Q17: =SUM(D17:P17)
B18: 交通費 | D18: 10000 | E18: 10000 | F18: 10000 | G18: 10000 | H18: 10000 | I18: 10000 | J18: 10000 | K18: 10000 | L18: 10000 | M18: 10000 | N18: 10000 | O18: 10000 | P18: 10000 | Q18: =SUM(D18:P18)
B19: 人件費（アルバイト） 計 ← PLシートの「人件費（アルバイト）」に連動 | C19: 人件費（アルバイト） | D19: =D17+D18 | E19: =E17+E18 | F19: =F17+F18 | G19: =G17+G18 | H19: =H17+H18 | I19: =I17+I18 | J19: =J17+J18 | K19: =K17+K18 | ... P19: =P17+P18 | Q19: =SUM(D19:P19)
B21: ▌ 広告宣伝費・イベント費
B22: SNS広告（Instagram/X） | D22: 60000 | E22: 60000 | F22: 60000 | G22: 60000 | H22: 60000 | I22: 60000 | J22: 60000 | K22: 60000 | L22: 60000 | M22: 60000 | N22: 60000 | O22: 60000 | P22: 60000 | Q22: =SUM(D22:P22)
B23: イベント出展費 | D23: 50000 | E23: 50000 | F23: 50000 | G23: 50000 | H23: 50000 | I23: 50000 | J23: 50000 | K23: 50000 | L23: 50000 | M23: 50000 | N23: 50000 | O23: 50000 | P23: 50000 | Q23: =SUM(D23:P23)
B24: 販促物・スリーブ等 | D24: 20000 | E24: 20000 | F24: 20000 | G24: 20000 | H24: 20000 | I24: 20000 | J24: 20000 | K24: 20000 | L24: 20000 | M24: 20000 | N24: 20000 | O24: 20000 | P24: 20000 | Q24: =SUM(D24:P24)
B25: 広告宣伝費・イベント費 計 ← PLシートの「広告宣伝費・イベント費」に連動 | C25: 広告宣伝費・イベント費 | D25: =D22+D23+D24 | E25: =E22+E23+E24 | F25: =F22+F23+F24 | G25: =G22+G23+G24 | H25: =H22+H23+H24 | I25: =I22+I23+I24 | J25: =J22+J23+J24 | K25: =K22+K23+K24 | ... P25: =P22+P23+P24 | Q25: =SUM(D25:P25)
B27: ▌ EC決済手数料
B28: メルカリShops手数料（約1%） | D28: 70000 | E28: 70000 | F28: 70000 | G28: 70000 | H28: 70000 | I28: 70000 | J28: 70000 | K28: 70000 | L28: 70000 | M28: 70000 | N28: 70000 | O28: 70000 | P28: 70000 | Q28: =SUM(D28:P28)
B29: クレジットカード決済手数料（約1%） | D29: 70000 | E29: 70000 | F29: 70000 | G29: 70000 | H29: 70000 | I29: 70000 | J29: 70000 | K29: 70000 | L29: 70000 | M29: 70000 | N29: 70000 | O29: 70000 | P29: 70000 | Q29: =SUM(D29:P29)
B30: EC決済手数料 計 ← PLシートの「EC決済手数料」に連動 | C30: EC決済手数料 | D30: =D28+D29 | E30: =E28+E29 | F30: =F28+F29 | G30: =G28+G29 | H30: =H28+H29 | I30: =I28+I29 | J30: =J28+J29 | K30: =K28+K29 | ... P30: =P28+P29 | Q30: =SUM(D30:P30)
B32: ▌ 荷造運賃
B33: 発送資材（段ボール・プチプチ等） | D33: 30000 | E33: 30000 | F33: 30000 | G33: 30000 | H33: 30000 | I33: 30000 | J33: 30000 | K33: 30000 | L33: 30000 | M33: 30000 | N33: 30000 | O33: 30000 | P33: 30000 | Q33: =SUM(D33:P33)
B34: 配送費（ヤマト・佐川等） | D34: 70000 | E34: 70000 | F34: 70000 | G34: 70000 | H34: 70000 | I34: 70000 | J34: 70000 | K34: 70000 | L34: 70000 | M34: 70000 | N34: 70000 | O34: 70000 | P34: 70000 | Q34: =SUM(D34:P34)
B35: 荷造運賃 計 ← PLシートの「荷造運賃」に連動 | C35: 荷造運賃 | D35: =D33+D34 | E35: =E33+E34 | F35: =F33+F34 | G35: =G33+G34 | H35: =H33+H34 | I35: =I33+I34 | J35: =J33+J34 | K35: =K33+K34 | ... P35: =P33+P34 | Q35: =SUM(D35:P35)
B37: ▌ 水道光熱費・システム・その他
B38: 電気代 | D38: 30000 | E38: 30000 | F38: 30000 | G38: 30000 | H38: 30000 | I38: 30000 | J38: 30000 | K38: 30000 | L38: 30000 | M38: 30000 | N38: 30000 | O38: 30000 | P38: 30000 | Q38: =SUM(D38:P38)
B39: POSシステム（STORES・スマレジ等） | D39: 15000 | E39: 15000 | F39: 15000 | G39: 15000 | H39: 15000 | I39: 15000 | J39: 15000 | K39: 15000 | L39: 15000 | M39: 15000 | N39: 15000 | O39: 15000 | P39: 15000 | Q39: =SUM(D39:P39)
B40: 会計ソフト（freee等） | D40: 5000 | E40: 5000 | F40: 5000 | G40: 5000 | H40: 5000 | I40: 5000 | J40: 5000 | K40: 5000 | L40: 5000 | M40: 5000 | N40: 5000 | O40: 5000 | P40: 5000 | Q40: =SUM(D40:P40)
B41: 通信費 | D41: 10000 | E41: 10000 | F41: 10000 | G41: 10000 | H41: 10000 | I41: 10000 | J41: 10000 | K41: 10000 | L41: 10000 | M41: 10000 | N41: 10000 | O41: 10000 | P41: 10000 | Q41: =SUM(D41:P41)
B42: 雑費・消耗品 | D42: 20000 | E42: 20000 | F42: 20000 | G42: 20000 | H42: 20000 | I42: 20000 | J42: 20000 | K42: 20000 | L42: 20000 | M42: 20000 | N42: 20000 | O42: 20000 | P42: 20000 | Q42: =SUM(D42:P42)
B43: 水道光熱費・システム・その他 計 ← PLシートの「水道光熱費・システム・その他」に連動 | C43: 水道光熱費・システム・その他 | D43: =D38+D39+D40+D41+D42 | E43: =E38+E39+E40+E41+E42 | F43: =F38+F39+F40+F41+F42 | G43: =G38+G39+G40+G41+G42 | H43: =H38+H39+H40+H41+H42 | I43: =I38+I39+I40+I41+I42 | J43: =J38+J39+J40+J41+J42 | K43: =K38+K39+K40+K41+K42 | ... P43: =P38+P39+P40+P41+P42 | Q43: =SUM(D43:P43)
B46: ▌ 販管費 総合計 | C46: 合 計 | D46: =D8+D14+D19+D25+D30+D35+D43 | E46: =E8+E14+E19+E25+E30+E35+E43 | F46: =F8+F14+F19+F25+F30+F35+F43 | G46: =G8+G14+G19+G25+G30+G35+G43 | H46: =H8+H14+H19+H25+H30+H35+H43 | I46: =I8+I14+I19+I25+I30+I35+I43 | J46: =J8+J14+J19+J25+J30+J35+J43 | K46: =K8+K14+K19+K25+K30+K35+K43 | ... P46: =P8+P14+P19+P25+P30+P35+P43 | Q46: =SUM(D46:P46)

Sheet ダッシュボード
B2: ダッシュボード ｜ 月次営業利益200万円 達成モニタリング
B3: ※ 各数値はPLシート・販管費内訳シートと連動しています。数値を変更するとこのシートも自動更新されます。
B5: 📊 年間サマリー（13ヶ月合計）
B6: 年間売上合計 | C6: 年間粗利 | D6: 年間販管費 | E6: 年間営業利益 ★
B7: ='月次PL'!P9 | C7: ='月次PL'!P16 | D7: ='月次PL'!P26 | E7: ='月次PL'!P28
B8: =IFERROR('月次PL'!P9/13,0) | C8: =IFERROR('月次PL'!P16/13,0) | D8: =IFERROR('月次PL'!P26/13,0) | E8: =IFERROR('月次PL'!P28/13,0)
B10: 📅 月次推移 （粗利 / 販管費 / 営業利益）
B11: 月 | C11: 売上合計 | D11: 粗利 | E11: 販管費 | F11: 営業利益
B12: 2026年7月 | C12: ='月次PL'!C9 | D12: ='月次PL'!C16 | E12: ='月次PL'!C26 | F12: ='月次PL'!C28
B13: 2026年8月 | C13: ='月次PL'!D9 | D13: ='月次PL'!D16 | E13: ='月次PL'!D26 | F13: ='月次PL'!D28
B14: 2026年9月 | C14: ='月次PL'!E9 | D14: ='月次PL'!E16 | E14: ='月次PL'!E26 | F14: ='月次PL'!E28
B15: 2026年10月 | C15: ='月次PL'!F9 | D15: ='月次PL'!F16 | E15: ='月次PL'!F26 | F15: ='月次PL'!F28
B16: 2026年11月 | C16: ='月次PL'!G9 | D16: ='月次PL'!G16 | E16: ='月次PL'!G26 | F16: ='月次PL'!G28
B17: 2026年12月 | C17: ='月次PL'!H9 | D17: ='月次PL'!H16 | E17: ='月次PL'!H26 | F17: ='月次PL'!H28
B18: 2027年1月 | C18: ='月次PL'!I9 | D18: ='月次PL'!I16 | E18: ='月次PL'!I26 | F18: ='月次PL'!I28
B19: 2027年2月 | C19: ='月次PL'!J9 | D19: ='月次PL'!J16 | E19: ='月次PL'!J26 | F19: ='月次PL'!J28
B20: 2027年3月 | C20: ='月次PL'!K9 | D20: ='月次PL'!K16 | E20: ='月次PL'!K26 | F20: ='月次PL'!K28
B21: 2027年4月 | C21: ='月次PL'!L9 | D21: ='月次PL'!L16 | E21: ='月次PL'!L26 | F21: ='月次PL'!L28
B22: 2027年5月 | C22: ='月次PL'!M9 | D22: ='月次PL'!M16 | E22: ='月次PL'!M26 | F22: ='月次PL'!M28
B23: 2027年6月 | C23: ='月次PL'!N9 | D23: ='月次PL'!N16 | E23: ='月次PL'!N26 | F23: ='月次PL'!N28
B24: 2027年7月 | C24: ='月次PL'!O9 | D24: ='月次PL'!O16 | E24: ='月次PL'!O26 | F24: ='月次PL'!O28
B25: 年間合計 | C25: ='月次PL'!P9 | D25: ='月次PL'!P16 | E25: ='月次PL'!P26 | F25: ='月次PL'!P28
B27: 📈 収益性指標（年間ベース）
B28: 粗利率 | C28: 営業利益率 | D28: 販管費比率
B29: =IFERROR('月次PL'!P16/'月次PL'!P9*100,0) | C29: =IFERROR('月次PL'!P28/'月次PL'!P9*100,0) | D29: =IFERROR('月次PL'!P26/'月次PL'!P9*100,0)
