Workbook

Sheet 3パターン比較概要
B2: トレーディングカードショップ 3パターン年間PLシミュレーション
B3: 期間：2026年7月〜2027年7月（13ヶ月） 単位：円 ※数値を変更すると全シートが自動連動します
B5: 項 目 | C5: パターンA EC特化（無店舗） | D5: パターンB 大型実店舗 | E5: パターンC ハイブリッド
B6: ▌ 売上高
B7: 新品売上 | C7: ='パターンA_EC特化'!P7 | D7: ='パターンB_大型実店舗'!P7 | E7: ='パターンC_ハイブリッド'!P7
B8: 中古売上 | C8: ='パターンA_EC特化'!P8 | D8: ='パターンB_大型実店舗'!P8 | E8: ='パターンC_ハイブリッド'!P8
B9: 売上合計 | C9: ='パターンA_EC特化'!P9 | D9: ='パターンB_大型実店舗'!P9 | E9: ='パターンC_ハイブリッド'!P9
B11: ▌ 売上原価
B12: 新品原価 | C12: ='パターンA_EC特化'!P12 | D12: ='パターンB_大型実店舗'!P12 | E12: ='パターンC_ハイブリッド'!P12
B13: 中古原価 | C13: ='パターンA_EC特化'!P13 | D13: ='パターンB_大型実店舗'!P13 | E13: ='パターンC_ハイブリッド'!P13
B14: 原価合計 | C14: ='パターンA_EC特化'!P14 | D14: ='パターンB_大型実店舗'!P14 | E14: ='パターンC_ハイブリッド'!P14
B16: ▌ 売上総利益（粗利） | C16: ='パターンA_EC特化'!P16 | D16: ='パターンB_大型実店舗'!P16 | E16: ='パターンC_ハイブリッド'!P16
B18: ▌ 販売管理費
B19: 地代家賃 | C19: ='パターンA_EC特化'!P19 | D19: ='パターンB_大型実店舗'!P19 | E19: ='パターンC_ハイブリッド'!P19
B20: 人件費（正社員） | C20: ='パターンA_EC特化'!P20 | D20: ='パターンB_大型実店舗'!P20 | E20: ='パターンC_ハイブリッド'!P20
B21: 人件費（アルバイト） | C21: ='パターンA_EC特化'!P21 | D21: ='パターンB_大型実店舗'!P21 | E21: ='パターンC_ハイブリッド'!P21
B22: 広告・イベント費 | C22: ='パターンA_EC特化'!P22 | D22: ='パターンB_大型実店舗'!P22 | E22: ='パターンC_ハイブリッド'!P22
B23: EC決済手数料 | C23: ='パターンA_EC特化'!P23 | D23: ='パターンB_大型実店舗'!P23 | E23: ='パターンC_ハイブリッド'!P23
B24: 荷造運賃 | C24: ='パターンA_EC特化'!P24 | D24: ='パターンB_大型実店舗'!P24 | E24: ='パターンC_ハイブリッド'!P24
B25: 水道光熱費等 | C25: ='パターンA_EC特化'!P25 | D25: ='パターンB_大型実店舗'!P25 | E25: ='パターンC_ハイブリッド'!P25
B26: 販管費合計 | C26: ='パターンA_EC特化'!P26 | D26: ='パターンB_大型実店舗'!P26 | E26: ='パターンC_ハイブリッド'!P26
B28: ▌ 営業利益 | C28: ='パターンA_EC特化'!P28 | D28: ='パターンB_大型実店舗'!P28 | E28: ='パターンC_ハイブリッド'!P28
B32: ★ 年間サマリー比較
B33: 指標 | C33: パターンA | D33: パターンB | E33: パターンC
B34: 年間売上合計 | C34: ='パターンA_EC特化'!P9 | D34: ='パターンB_大型実店舗'!P9 | E34: ='パターンC_ハイブリッド'!P9
B35: 年間粗利 | C35: ='パターンA_EC特化'!P16 | D35: ='パターンB_大型実店舗'!P16 | E35: ='パターンC_ハイブリッド'!P16
B36: 年間販管費合計 | C36: ='パターンA_EC特化'!P26 | D36: ='パターンB_大型実店舗'!P26 | E36: ='パターンC_ハイブリッド'!P26
B37: 年間営業利益 | C37: ='パターンA_EC特化'!P28 | D37: ='パターンB_大型実店舗'!P28 | E37: ='パターンC_ハイブリッド'!P28
B39: ★ 収益性指標（年間）
B40: 指標 | C40: パターンA | D40: パターンB | E40: パターンC
B41: 粗利率（%） | C41: =IFERROR('パターンA_EC特化'!P16/'パターンA_EC特化'!P9*100,0) | D41: =IFERROR('パターンB_大型実店舗'!P16/'パターンB_大型実店舗'!P9*100,0) | E41: =IFERROR('パターンC_ハイブリッド'!P16/'パターンC_ハイブリッド'!P9*100,0)
B42: 営業利益率（%） | C42: =IFERROR('パターンA_EC特化'!P28/'パターンA_EC特化'!P9*100,0) | D42: =IFERROR('パターンB_大型実店舗'!P28/'パターンB_大型実店舗'!P9*100,0) | E42: =IFERROR('パターンC_ハイブリッド'!P28/'パターンC_ハイブリッド'!P9*100,0)

Sheet パターンA_EC特化
B2: 月次PLシミュレーション EC特化（無店舗）
B3: 期間：2026年7月〜2027年7月（13ヶ月） 単位：円
B5: 項 目 | C5: 2026年7月 | D5: 2026年8月 | E5: 2026年9月 | F5: 2026年10月 | G5: 2026年11月 | H5: 2026年12月 | I5: 2027年1月 | J5: 2027年2月 | K5: 2027年3月 | L5: 2027年4月 | M5: 2027年5月 | N5: 2027年6月 | O5: 2027年7月 | P5: 年間合計
B6: ▌ 売上高
B7: 新品売上 | C7: 2100000 | D7: 2100000 | E7: 2100000 | F7: 2100000 | G7: 2100000 | H7: 2100000 | I7: 2100000 | J7: 2100000 | K7: 2100000 | L7: 2100000 | M7: 2100000 | N7: 2100000 | O7: 2100000 | P7: =SUM(C7:O7)
B8: 中古売上 | C8: 900000 | D8: 900000 | E8: 900000 | F8: 900000 | G8: 900000 | H8: 900000 | I8: 900000 | J8: 900000 | K8: 900000 | L8: 900000 | M8: 900000 | N8: 900000 | O8: 900000 | P8: =SUM(C8:O8)
B9: 売上合計 | C9: =C7+C8 | D9: =D7+D8 | E9: =E7+E8 | F9: =F7+F8 | G9: =G7+G8 | H9: =H7+H8 | I9: =I7+I8 | J9: =J7+J8 | ... O9: =O7+O8 | P9: =SUM(C9:O9)
B11: ▌ 売上原価
B12: 新品原価 | C12: =ROUND(C7*0.7,0) | D12: =ROUND(D7*0.7,0) | E12: =ROUND(E7*0.7,0) | F12: =ROUND(F7*0.7,0) | G12: =ROUND(G7*0.7,0) | H12: =ROUND(H7*0.7,0) | I12: =ROUND(I7*0.7,0) | J12: =ROUND(J7*0.7,0) | ... O12: =ROUND(O7*0.7,0) | P12: =SUM(C12:O12)
B13: 中古原価 | C13: =ROUND(C8*0.5,0) | D13: =ROUND(D8*0.5,0) | E13: =ROUND(E8*0.5,0) | F13: =ROUND(F8*0.5,0) | G13: =ROUND(G8*0.5,0) | H13: =ROUND(H8*0.5,0) | I13: =ROUND(I8*0.5,0) | J13: =ROUND(J8*0.5,0) | ... O13: =ROUND(O8*0.5,0) | P13: =SUM(C13:O13)
B14: 原価合計 | C14: =C12+C13 | D14: =D12+D13 | E14: =E12+E13 | F14: =F12+F13 | G14: =G12+G13 | H14: =H12+H13 | I14: =I12+I13 | J14: =J12+J13 | ... O14: =O12+O13 | P14: =SUM(C14:O14)
B16: ▌ 売上総利益（粗利） | C16: =C9-C14 | D16: =D9-D14 | E16: =E9-E14 | F16: =F9-F14 | G16: =G9-G14 | H16: =H9-H14 | I16: =I9-I14 | J16: =J9-J14 | ... O16: =O9-O14 | P16: =SUM(C16:O16)
B18: ▌ 販売管理費
B19: 地代家賃 | C19: 0 | D19: 0 | E19: 0 | F19: 0 | G19: 0 | H19: 0 | I19: 0 | J19: 0 | K19: 0 | L19: 0 | M19: 0 | N19: 0 | O19: 0 | P19: =SUM(C19:O19)
B20: 人件費（正社員） | C20: 350000 | D20: 350000 | E20: 350000 | F20: 350000 | G20: 350000 | H20: 350000 | I20: 350000 | J20: 350000 | K20: 350000 | L20: 350000 | M20: 350000 | N20: 350000 | O20: 350000 | P20: =SUM(C20:O20)
B21: 人件費（アルバイト） | C21: 0 | D21: 0 | E21: 0 | F21: 0 | G21: 0 | H21: 0 | I21: 0 | J21: 0 | K21: 0 | L21: 0 | M21: 0 | N21: 0 | O21: 0 | P21: =SUM(C21:O21)
B22: 広告宣伝費・イベント費 | C22: 50000 | D22: 50000 | E22: 50000 | F22: 50000 | G22: 50000 | H22: 50000 | I22: 50000 | J22: 50000 | K22: 50000 | L22: 50000 | M22: 50000 | N22: 50000 | O22: 50000 | P22: =SUM(C22:O22)
B23: EC決済手数料 | C23: =ROUND(C9*0.035,0) | D23: =ROUND(D9*0.035,0) | E23: =ROUND(E9*0.035,0) | F23: =ROUND(F9*0.035,0) | G23: =ROUND(G9*0.035,0) | H23: =ROUND(H9*0.035,0) | I23: =ROUND(I9*0.035,0) | J23: =ROUND(J9*0.035,0) | ... O23: =ROUND(O9*0.035,0) | P23: =SUM(C23:O23)
B24: 荷造運賃 | C24: 80000 | D24: 80000 | E24: 80000 | F24: 80000 | G24: 80000 | H24: 80000 | I24: 80000 | J24: 80000 | K24: 80000 | L24: 80000 | M24: 80000 | N24: 80000 | O24: 80000 | P24: =SUM(C24:O24)
B25: 水道光熱費・システム・その他 | C25: 50000 | D25: 50000 | E25: 50000 | F25: 50000 | G25: 50000 | H25: 50000 | I25: 50000 | J25: 50000 | K25: 50000 | L25: 50000 | M25: 50000 | N25: 50000 | O25: 50000 | P25: =SUM(C25:O25)
B26: 販管費合計 | C26: =C19+C20+C21+C22+C23+C24+C25 | D26: =D19+D20+D21+D22+D23+D24+D25 | E26: =E19+E20+E21+E22+E23+E24+E25 | F26: =F19+F20+F21+F22+F23+F24+F25 | G26: =G19+G20+G21+G22+G23+G24+G25 | H26: =H19+H20+H21+H22+H23+H24+H25 | I26: =I19+I20+I21+I22+I23+I24+I25 | J26: =J19+J20+J21+J22+J23+J24+J25 | ... O26: =O19+O20+O21+O22+O23+O24+O25 | P26: =SUM(C26:O26)
B28: ▌ 営業利益 | C28: =C16-C26 | D28: =D16-D26 | E28: =E16-E26 | F28: =F16-F26 | G28: =G16-G26 | H28: =H16-H26 | I28: =I16-I26 | J28: =J16-J26 | ... O28: =O16-O26 | P28: =SUM(C28:O28)
B31: 【主要仮定値】
B32: 新品売上（月次） | C32: 2,100,000 円
B33: 中古売上（月次） | C33: 900,000 円
B34: 新品原価率 | C34: 70%
B35: 中古原価率 | C35: 50%
B36: 地代家賃 | C36: 0 円
B37: 人件費（正社員） | C37: 350,000 円
B38: 人件費（アルバイト） | C38: 0 円
B39: 広告・イベント費 | C39: 50,000 円
B40: EC手数料率 | C40: 3.5%
B41: 荷造運賃 | C41: 80,000 円
B42: 水道光熱費等 | C42: 50,000 円

Sheet パターンB_大型実店舗
B2: 月次PLシミュレーション 大型実店舗
B3: 期間：2026年7月〜2027年7月（13ヶ月） 単位：円
B5: 項 目 | C5: 2026年7月 | D5: 2026年8月 | E5: 2026年9月 | F5: 2026年10月 | G5: 2026年11月 | H5: 2026年12月 | I5: 2027年1月 | J5: 2027年2月 | K5: 2027年3月 | L5: 2027年4月 | M5: 2027年5月 | N5: 2027年6月 | O5: 2027年7月 | P5: 年間合計
B6: ▌ 売上高
B7: 新品売上 | C7: 5600000 | D7: 5600000 | E7: 5600000 | F7: 5600000 | G7: 5600000 | H7: 5600000 | I7: 5600000 | J7: 5600000 | K7: 5600000 | L7: 5600000 | M7: 5600000 | N7: 5600000 | O7: 5600000 | P7: =SUM(C7:O7)
B8: 中古売上 | C8: 2400000 | D8: 2400000 | E8: 2400000 | F8: 2400000 | G8: 2400000 | H8: 2400000 | I8: 2400000 | J8: 2400000 | K8: 2400000 | L8: 2400000 | M8: 2400000 | N8: 2400000 | O8: 2400000 | P8: =SUM(C8:O8)
B9: 売上合計 | C9: =C7+C8 | D9: =D7+D8 | E9: =E7+E8 | F9: =F7+F8 | G9: =G7+G8 | H9: =H7+H8 | I9: =I7+I8 | J9: =J7+J8 | ... O9: =O7+O8 | P9: =SUM(C9:O9)
B11: ▌ 売上原価
B12: 新品原価 | C12: =ROUND(C7*0.7,0) | D12: =ROUND(D7*0.7,0) | E12: =ROUND(E7*0.7,0) | F12: =ROUND(F7*0.7,0) | G12: =ROUND(G7*0.7,0) | H12: =ROUND(H7*0.7,0) | I12: =ROUND(I7*0.7,0) | J12: =ROUND(J7*0.7,0) | ... O12: =ROUND(O7*0.7,0) | P12: =SUM(C12:O12)
B13: 中古原価 | C13: =ROUND(C8*0.5,0) | D13: =ROUND(D8*0.5,0) | E13: =ROUND(E8*0.5,0) | F13: =ROUND(F8*0.5,0) | G13: =ROUND(G8*0.5,0) | H13: =ROUND(H8*0.5,0) | I13: =ROUND(I8*0.5,0) | J13: =ROUND(J8*0.5,0) | ... O13: =ROUND(O8*0.5,0) | P13: =SUM(C13:O13)
B14: 原価合計 | C14: =C12+C13 | D14: =D12+D13 | E14: =E12+E13 | F14: =F12+F13 | G14: =G12+G13 | H14: =H12+H13 | I14: =I12+I13 | J14: =J12+J13 | ... O14: =O12+O13 | P14: =SUM(C14:O14)
B16: ▌ 売上総利益（粗利） | C16: =C9-C14 | D16: =D9-D14 | E16: =E9-E14 | F16: =F9-F14 | G16: =G9-G14 | H16: =H9-H14 | I16: =I9-I14 | J16: =J9-J14 | ... O16: =O9-O14 | P16: =SUM(C16:O16)
B18: ▌ 販売管理費
B19: 地代家賃 | C19: 300000 | D19: 300000 | E19: 300000 | F19: 300000 | G19: 300000 | H19: 300000 | I19: 300000 | J19: 300000 | K19: 300000 | L19: 300000 | M19: 300000 | N19: 300000 | O19: 300000 | P19: =SUM(C19:O19)
B20: 人件費（正社員） | C20: 350000 | D20: 350000 | E20: 350000 | F20: 350000 | G20: 350000 | H20: 350000 | I20: 350000 | J20: 350000 | K20: 350000 | L20: 350000 | M20: 350000 | N20: 350000 | O20: 350000 | P20: =SUM(C20:O20)
B21: 人件費（アルバイト） | C21: 250000 | D21: 250000 | E21: 250000 | F21: 250000 | G21: 250000 | H21: 250000 | I21: 250000 | J21: 250000 | K21: 250000 | L21: 250000 | M21: 250000 | N21: 250000 | O21: 250000 | P21: =SUM(C21:O21)
B22: 広告宣伝費・イベント費 | C22: 150000 | D22: 150000 | E22: 150000 | F22: 150000 | G22: 150000 | H22: 150000 | I22: 150000 | J22: 150000 | K22: 150000 | L22: 150000 | M22: 150000 | N22: 150000 | O22: 150000 | P22: =SUM(C22:O22)
B23: EC決済手数料 | C23: =ROUND(C9*0.015,0) | D23: =ROUND(D9*0.015,0) | E23: =ROUND(E9*0.015,0) | F23: =ROUND(F9*0.015,0) | G23: =ROUND(G9*0.015,0) | H23: =ROUND(H9*0.015,0) | I23: =ROUND(I9*0.015,0) | J23: =ROUND(J9*0.015,0) | ... O23: =ROUND(O9*0.015,0) | P23: =SUM(C23:O23)
B24: 荷造運賃 | C24: 80000 | D24: 80000 | E24: 80000 | F24: 80000 | G24: 80000 | H24: 80000 | I24: 80000 | J24: 80000 | K24: 80000 | L24: 80000 | M24: 80000 | N24: 80000 | O24: 80000 | P24: =SUM(C24:O24)
B25: 水道光熱費・システム・その他 | C25: 120000 | D25: 120000 | E25: 120000 | F25: 120000 | G25: 120000 | H25: 120000 | I25: 120000 | J25: 120000 | K25: 120000 | L25: 120000 | M25: 120000 | N25: 120000 | O25: 120000 | P25: =SUM(C25:O25)
B26: 販管費合計 | C26: =C19+C20+C21+C22+C23+C24+C25 | D26: =D19+D20+D21+D22+D23+D24+D25 | E26: =E19+E20+E21+E22+E23+E24+E25 | F26: =F19+F20+F21+F22+F23+F24+F25 | G26: =G19+G20+G21+G22+G23+G24+G25 | H26: =H19+H20+H21+H22+H23+H24+H25 | I26: =I19+I20+I21+I22+I23+I24+I25 | J26: =J19+J20+J21+J22+J23+J24+J25 | ... O26: =O19+O20+O21+O22+O23+O24+O25 | P26: =SUM(C26:O26)
B28: ▌ 営業利益 | C28: =C16-C26 | D28: =D16-D26 | E28: =E16-E26 | F28: =F16-F26 | G28: =G16-G26 | H28: =H16-H26 | I28: =I16-I26 | J28: =J16-J26 | ... O28: =O16-O26 | P28: =SUM(C28:O28)
B31: 【主要仮定値】
B32: 新品売上（月次） | C32: 5,600,000 円
B33: 中古売上（月次） | C33: 2,400,000 円
B34: 新品原価率 | C34: 70%
B35: 中古原価率 | C35: 50%
B36: 地代家賃 | C36: 300,000 円
B37: 人件費（正社員） | C37: 350,000 円
B38: 人件費（アルバイト） | C38: 250,000 円
B39: 広告・イベント費 | C39: 150,000 円
B40: EC手数料率 | C40: 1.5%
B41: 荷造運賃 | C41: 80,000 円
B42: 水道光熱費等 | C42: 120,000 円

Sheet パターンC_ハイブリッド
B2: 月次PLシミュレーション ハイブリッド（実店舗＋EC）
B3: 期間：2026年7月〜2027年7月（13ヶ月） 単位：円
B5: 項 目 | C5: 2026年7月 | D5: 2026年8月 | E5: 2026年9月 | F5: 2026年10月 | G5: 2026年11月 | H5: 2026年12月 | I5: 2027年1月 | J5: 2027年2月 | K5: 2027年3月 | L5: 2027年4月 | M5: 2027年5月 | N5: 2027年6月 | O5: 2027年7月 | P5: 年間合計
B6: ▌ 売上高
B7: 新品売上 | C7: 3500000 | D7: 3500000 | E7: 3500000 | F7: 3500000 | G7: 3500000 | H7: 3500000 | I7: 3500000 | J7: 3500000 | K7: 3500000 | L7: 3500000 | M7: 3500000 | N7: 3500000 | O7: 3500000 | P7: =SUM(C7:O7)
B8: 中古売上 | C8: 1500000 | D8: 1500000 | E8: 1500000 | F8: 1500000 | G8: 1500000 | H8: 1500000 | I8: 1500000 | J8: 1500000 | K8: 1500000 | L8: 1500000 | M8: 1500000 | N8: 1500000 | O8: 1500000 | P8: =SUM(C8:O8)
B9: 売上合計 | C9: =C7+C8 | D9: =D7+D8 | E9: =E7+E8 | F9: =F7+F8 | G9: =G7+G8 | H9: =H7+H8 | I9: =I7+I8 | J9: =J7+J8 | ... O9: =O7+O8 | P9: =SUM(C9:O9)
B11: ▌ 売上原価
B12: 新品原価 | C12: =ROUND(C7*0.7,0) | D12: =ROUND(D7*0.7,0) | E12: =ROUND(E7*0.7,0) | F12: =ROUND(F7*0.7,0) | G12: =ROUND(G7*0.7,0) | H12: =ROUND(H7*0.7,0) | I12: =ROUND(I7*0.7,0) | J12: =ROUND(J7*0.7,0) | ... O12: =ROUND(O7*0.7,0) | P12: =SUM(C12:O12)
B13: 中古原価 | C13: =ROUND(C8*0.5,0) | D13: =ROUND(D8*0.5,0) | E13: =ROUND(E8*0.5,0) | F13: =ROUND(F8*0.5,0) | G13: =ROUND(G8*0.5,0) | H13: =ROUND(H8*0.5,0) | I13: =ROUND(I8*0.5,0) | J13: =ROUND(J8*0.5,0) | ... O13: =ROUND(O8*0.5,0) | P13: =SUM(C13:O13)
B14: 原価合計 | C14: =C12+C13 | D14: =D12+D13 | E14: =E12+E13 | F14: =F12+F13 | G14: =G12+G13 | H14: =H12+H13 | I14: =I12+I13 | J14: =J12+J13 | ... O14: =O12+O13 | P14: =SUM(C14:O14)
B16: ▌ 売上総利益（粗利） | C16: =C9-C14 | D16: =D9-D14 | E16: =E9-E14 | F16: =F9-F14 | G16: =G9-G14 | H16: =H9-H14 | I16: =I9-I14 | J16: =J9-J14 | ... O16: =O9-O14 | P16: =SUM(C16:O16)
B18: ▌ 販売管理費
B19: 地代家賃 | C19: 150000 | D19: 150000 | E19: 150000 | F19: 150000 | G19: 150000 | H19: 150000 | I19: 150000 | J19: 150000 | K19: 150000 | L19: 150000 | M19: 150000 | N19: 150000 | O19: 150000 | P19: =SUM(C19:O19)
B20: 人件費（正社員） | C20: 350000 | D20: 350000 | E20: 350000 | F20: 350000 | G20: 350000 | H20: 350000 | I20: 350000 | J20: 350000 | K20: 350000 | L20: 350000 | M20: 350000 | N20: 350000 | O20: 350000 | P20: =SUM(C20:O20)
B21: 人件費（アルバイト） | C21: 80000 | D21: 80000 | E21: 80000 | F21: 80000 | G21: 80000 | H21: 80000 | I21: 80000 | J21: 80000 | K21: 80000 | L21: 80000 | M21: 80000 | N21: 80000 | O21: 80000 | P21: =SUM(C21:O21)
B22: 広告宣伝費・イベント費 | C22: 80000 | D22: 80000 | E22: 80000 | F22: 80000 | G22: 80000 | H22: 80000 | I22: 80000 | J22: 80000 | K22: 80000 | L22: 80000 | M22: 80000 | N22: 80000 | O22: 80000 | P22: =SUM(C22:O22)
B23: EC決済手数料 | C23: =ROUND(C9*0.025,0) | D23: =ROUND(D9*0.025,0) | E23: =ROUND(E9*0.025,0) | F23: =ROUND(F9*0.025,0) | G23: =ROUND(G9*0.025,0) | H23: =ROUND(H9*0.025,0) | I23: =ROUND(I9*0.025,0) | J23: =ROUND(J9*0.025,0) | ... O23: =ROUND(O9*0.025,0) | P23: =SUM(C23:O23)
B24: 荷造運賃 | C24: 80000 | D24: 80000 | E24: 80000 | F24: 80000 | G24: 80000 | H24: 80000 | I24: 80000 | J24: 80000 | K24: 80000 | L24: 80000 | M24: 80000 | N24: 80000 | O24: 80000 | P24: =SUM(C24:O24)
B25: 水道光熱費・システム・その他 | C25: 80000 | D25: 80000 | E25: 80000 | F25: 80000 | G25: 80000 | H25: 80000 | I25: 80000 | J25: 80000 | K25: 80000 | L25: 80000 | M25: 80000 | N25: 80000 | O25: 80000 | P25: =SUM(C25:O25)
B26: 販管費合計 | C26: =C19+C20+C21+C22+C23+C24+C25 | D26: =D19+D20+D21+D22+D23+D24+D25 | E26: =E19+E20+E21+E22+E23+E24+E25 | F26: =F19+F20+F21+F22+F23+F24+F25 | G26: =G19+G20+G21+G22+G23+G24+G25 | H26: =H19+H20+H21+H22+H23+H24+H25 | I26: =I19+I20+I21+I22+I23+I24+I25 | J26: =J19+J20+J21+J22+J23+J24+J25 | ... O26: =O19+O20+O21+O22+O23+O24+O25 | P26: =SUM(C26:O26)
B28: ▌ 営業利益 | C28: =C16-C26 | D28: =D16-D26 | E28: =E16-E26 | F28: =F16-F26 | G28: =G16-G26 | H28: =H16-H26 | I28: =I16-I26 | J28: =J16-J26 | ... O28: =O16-O26 | P28: =SUM(C28:O28)
B31: 【主要仮定値】
B32: 新品売上（月次） | C32: 3,500,000 円
B33: 中古売上（月次） | C33: 1,500,000 円
B34: 新品原価率 | C34: 70%
B35: 中古原価率 | C35: 50%
B36: 地代家賃 | C36: 150,000 円
B37: 人件費（正社員） | C37: 350,000 円
B38: 人件費（アルバイト） | C38: 80,000 円
B39: 広告・イベント費 | C39: 80,000 円
B40: EC手数料率 | C40: 2.5%
B41: 荷造運賃 | C41: 80,000 円
B42: 水道光熱費等 | C42: 80,000 円
