Workbook

Sheet 使い方
B2: トレカ在庫ポートフォリオ管理ブック
B3: スニダン等で扱うトレーディングカード（ポケモンカード／ワンピースカード／遊戯王 等）の在庫を4象限で管理するための運用テンプレートです。
B5: ■ シート構成
B6: 設定：4象限のしきい値、銘柄タイトル／希少性／トレンド／ボラティリティ／ステータスのマスタ、集中リスク集計用のキャラ・イラストレーターリストを管理します。まずこのシートを事業実態に合わせて調整してください。
B7: ウォッチリスト：スニダン等で気になっている未仕入れのカードを登録すると、想定売却日数と想定粗利率から自動で4象限に振り分けます。
B8: 仕入れ計画：象限ごとに「何を・いくらまで・どの希少性／トレンド／ボラティリティなら仕入れてよいか」のルールと月間予算配分を定義します。
B9: 在庫管理：実在庫を4分類＋タグ（キャラ／イラストレーター／絶版／周年／希少性／トレンド／ボラティリティ）で登録し、ポートフォリオ比率を自動計算します。
B10: ダッシュボード：資金効率（在庫の入れ替わり回数・資金倍率・含み損益率）と換金のしやすさ、偏りリスクを自動集計します。
B11: ■ 2段階の判断の仕組み
B12: ① 自動判定（象限）：「想定売却日数」と「想定粗利率」の2つの数値から、コア／回転／厳選／見送りの4象限を自動で判定します（「設定」シートのしきい値で調整可能）。
B13: ② 仕入れ可否の判断（属性）：象限が決まったら、そのカードの「希少性」「トレンド（値動きの勢い）」「ボラティリティ（値動きの荒さ）」が、その象限で仕入れてよい条件に当てはまるかを「仕入れ計画」シートと照らし合わせて判断します。
B14: ■ 入力ルール（色分け）
... B34: 偏りリスク(HHI)：特定のカテゴリ・キャラ・イラストレーターに在庫が偏っていないかを数値化したものです（集中度指数／HHI）。数値が大きいほど偏りが大きいことを意味します。目安：1,500未満＝分散、1,500〜2,500＝中程度、2,500以上＝偏りが大きい。

Sheet 設定
B2: 設定
B3: 4象限のしきい値とマスタデータ。事業実態に合わせて調整してください。
B5: ■ 4象限 自動判定しきい値（想定売却日数・想定粗利率から象限を機械的に判定）
B6: 早く売れる基準（想定売却日数・この日数以内なら「早く売れる」とみなす） | C6: 30
B7: 儲かる基準（想定粗利率・この率以上なら「利益率が高い」とみなす） | C7: 0.2
B8: 売れ残りリスク基準（想定売却日数がこの日数を超えたら要注意） | C8: 90
B9: ※ この2つのしきい値は象限の自動判定専用です。カードごとの仕入れ可否は「仕入れ計画」シートの希少性／トレンド／ボラティリティ条件で判断します。
B11: ■ 4象限マスタ（分類ロジック・方針の目安・投資フレームワークとの対応）
B12: 象限コード | C12: 早く売れる？ | D12: 利益率は高い？ | E12: 方針の目安 | F12: 投資フレームワークでの呼称 | G12: 資金配分の目安
B13: I(コア) | C13: 早い | D13: 高い | E13: 積極的に仕入れる中心銘柄。予算配分と在庫上限を厚めに。 | F13: コアポジション（収益基盤） | G13: 0.55
B14: II(回転) | C14: 早い | D14: 低い（薄利） | E14: 資金回転を稼ぐ数量枠。単価上限を抑えて回転数で稼ぐ。 | F14: キャッシュ同等物（リスクバッファ） | G14: 0.2
B15: III(厳選) | C15: 遅い | D15: 高い | E15: 資金拘束を許容できる範囲で少数厳選。上限点数を絞る。 | F15: グロース枠（将来リターン） | G15: 0.2
B16: IV(見送り) | C16: 遅い | D16: 低い（薄利） | E16: 原則仕入れ見送り。ウォッチのみ継続し再評価を待つ。 | F16: 劣後在庫（排除対象） | G16: 0.05
B17: ※ 「投資フレームワークでの呼称」「資金配分の目安」は社内の投資フレームワーク検討資料（コア・サテライト型：コアが過半・劣後は最小限）を参考にした値です。「仕入れ計画」シートの予算配分比率の初期値として反映しています。
B18: ■ 銘柄タイトルマスタ（トレカのタイトル。在庫管理・ウォッチリストのプルダウンで使用）
B19: 銘柄タイトル
B20: ポケモンカード
B21: ワンピースカード
B22: 遊戯王
B23: デュエル・マスターズ
B24: マジック：ザ・ギャザリング
B25: その他
B27: ■ 希少性マスタ（レアリティ。SSが最も希少）
B28: 希少性
B29: SS
... B41: ■ ボラティリティマスタ（価格の変動の荒さ・実効流動性の計算に使用）
B42: ボラティリティ | C42: 目減り係数
B43: 高 | C43: 1.5
B44: 中 | C44: 1.2
B45: 低 | C45: 1
B46: ※ 目減り係数：想定売却日数にこの係数を掛けて「実効想定売却日数」を算出します（値動きが荒いほど、安全に売り切るまでに実質的な時間がかかるとみなす）。
B47: ■ ステータスマスタ
B48: ステータス
B49: 在庫中
B50: 受注済
B51: 売却済
B53: ■ キャラクター集中リスク集計対象リスト（在庫管理シートで使うキャラ名を入力すると、ダッシュボードで自動集計されます。最大20件）
B54: キャラ名
B55: リザードン
B56: ルフィ
B57: 青眼の白龍
B76: ■ イラストレーター集中リスク集計対象リスト（最大20件）
... B123: ※ 相関ドライバーとは、複数の商材が同じ要因（人気投票・映画出演・再販発表・環境トップ入り等）で連動して値動きする際の共通要因です。ジャンル（銘柄タイトル）が分散していても、同じ収録弾・企画に在庫が偏っていると、その人気が落ちた瞬間に在庫全体が一緒に値下がりするリスクがあります。

Sheet ウォッチリスト
B2: ウォッチリスト（4象限分類）
B3: スニダン等のウォッチリスト登録分を入力すると、想定売却日数・想定粗利率から自動で4象限に振り分けます。青字セルのみ入力してください。
B5: ■ 象限別 候補数サマリー
B6: I(コア) 候補数 | C6: =COUNTIF(P13:P112,"I(コア)") -> 2
B7: II(回転) 候補数 | C7: =COUNTIF(P13:P112,"II(回転)") -> 1
B8: III(厳選) 候補数 | C8: =COUNTIF(P13:P112,"III(厳選)") -> 2
B9: IV(見送り) 候補数 | C9: =COUNTIF(P13:P112,"IV(見送り)") -> 1
A12: No | B12: 銘柄名 | C12: 銘柄タイトル | D12: 希少性 | E12: トレンド | F12: ボラティリティ | G12: スニダン参考価格 （現在相場） | H12: 想定仕入値 | I12: 想定売却価格 | J12: 想定売却 日数 | K12: 実効想定売却 日数（ボラ考慮） | L12: 想定粗利額 | M12: 想定粗利率 | N12: 資本効率 （利益率×回転率） | O12: ポジション サイズ目安 | P12: 象限 | Q12: 仕入れ判定 | R12: メモ
A13: =IF(B13="","",ROW()-12) -> 1 | B13: リザードンVMAX（ポケモンカード） | C13: ポケモンカード | D13: SS | E13: 上昇 | F13: 低 | G13: 28000 | H13: 22000 | I13: 32000 | J13: 15 | K13: =IF(B13="","",J13*IFERROR(INDEX(設定!$C$43:$C$45,MATCH(F13,設定!$B$43:$B$45,0)),1)) -> 15 | L13: =IF(B13="","",I13-H13) -> 10000 | M13: =IF(B13="","",IF(H13=0,"",L13/H13)) -> 0.45454545 | N13: =IF(B13="","",IF(J13=0,"",M13*365/J13)) -> 11.060606 | O13: =IF(B13="","",IFERROR(M13/INDEX(設定!$C$43:$C$45,MATCH(F13,設定!$B$43:$B$45,0)),"")) -> 0.45454545 | P13: =IF(B13="","",IF(J13<=設定!$C$6,IF(M13>=設定!$C$7,"I(コア)","II(回転)"),IF(M13>=設定!$C$7,"III(厳選)","IV(見送り)"))) -> I(コア) | Q13: =IF(B13="","",IF(OR(P13="I(コア)",P13="II(回転)"),"仕入れ候補",IF(P13="III(厳選)","厳選検討（少数）","見送り"))) -> 仕入れ候補
A14: =IF(B14="","",ROW()-12) -> 2 | B14: ルフィ SEC（ワンピースカード） | C14: ワンピースカード | D14: S | E14: 上昇 | F14: 中 | G14: 18000 | H14: 15000 | I14: 19500 | J14: 20 | K14: =IF(B14="","",J14*IFERROR(INDEX(設定!$C$43:$C$45,MATCH(F14,設定!$B$43:$B$45,0)),1)) -> 24 | L14: =IF(B14="","",I14-H14) -> 4500 | M14: =IF(B14="","",IF(H14=0,"",L14/H14)) -> 0.3 | N14: =IF(B14="","",IF(J14=0,"",M14*365/J14)) -> 5.475 | O14: =IF(B14="","",IFERROR(M14/INDEX(設定!$C$43:$C$45,MATCH(F14,設定!$B$43:$B$45,0)),"")) -> 0.25 | P14: =IF(B14="","",IF(J14<=設定!$C$6,IF(M14>=設定!$C$7,"I(コア)","II(回転)"),IF(M14>=設定!$C$7,"III(厳選)","IV(見送り)"))) -> I(コア) | Q14: =IF(B14="","",IF(OR(P14="I(コア)",P14="II(回転)"),"仕入れ候補",IF(P14="III(厳選)","厳選検討（少数）","見送り"))) -> 仕入れ候補
A15: =IF(B15="","",ROW()-12) -> 3 | B15: 青眼の白龍 初期（遊戯王） | C15: 遊戯王 | D15: SS | E15: 安定 | F15: 低 | G15: 45000 | H15: 38000 | I15: 52000 | J15: 60 | K15: =IF(B15="","",J15*IFERROR(INDEX(設定!$C$43:$C$45,MATCH(F15,設定!$B$43:$B$45,0)),1)) -> 60 | L15: =IF(B15="","",I15-H15) -> 14000 | M15: =IF(B15="","",IF(H15=0,"",L15/H15)) -> 0.36842105 | N15: =IF(B15="","",IF(J15=0,"",M15*365/J15)) -> 2.2412281 | O15: =IF(B15="","",IFERROR(M15/INDEX(設定!$C$43:$C$45,MATCH(F15,設定!$B$43:$B$45,0)),"")) -> 0.36842105 | P15: =IF(B15="","",IF(J15<=設定!$C$6,IF(M15>=設定!$C$7,"I(コア)","II(回転)"),IF(M15>=設定!$C$7,"III(厳選)","IV(見送り)"))) -> III(厳選) | Q15: =IF(B15="","",IF(OR(P15="I(コア)",P15="II(回転)"),"仕入れ候補",IF(P15="III(厳選)","厳選検討（少数）","見送り"))) -> 厳選検討（少数） | R15: 絶版・入手困難
A16: =IF(B16="","",ROW()-12) -> 4 | B16: ピカチュウ プロモ（ポケモンカード） | C16: ポケモンカード | D16: A | E16: 安定 | F16: 中 | G16: 9000 | H16: 7000 | I16: 8500 | J16: 45 | K16: =IF(B16="","",J16*IFERROR(INDEX(設定!$C$43:$C$45,MATCH(F16,設定!$B$43:$B$45,0)),1)) -> 54 | L16: =IF(B16="","",I16-H16) -> 1500 | M16: =IF(B16="","",IF(H16=0,"",L16/H16)) -> 0.21428571 | N16: =IF(B16="","",IF(J16=0,"",M16*365/J16)) -> 1.7380952 | O16: =IF(B16="","",IFERROR(M16/INDEX(設定!$C$43:$C$45,MATCH(F16,設定!$B$43:$B$45,0)),"")) -> 0.17857143 | P16: =IF(B16="","",IF(J16<=設定!$C$6,IF(M16>=設定!$C$7,"I(コア)","II(回転)"),IF(M16>=設定!$C$7,"III(厳選)","IV(見送り)"))) -> III(厳選) | Q16: =IF(B16="","",IF(OR(P16="I(コア)",P16="II(回転)"),"仕入れ候補",IF(P16="III(厳選)","厳選検討（少数）","見送り"))) -> 厳選検討（少数） | R16: 周年記念
A17: =IF(B17="","",ROW()-12) -> 5 | B17: 人気シングル（遊戯王） | C17: 遊戯王 | D17: A | E17: 上昇 | F17: 中 | G17: 12000 | H17: 10000 | I17: 11500 | J17: 10 | K17: =IF(B17="","",J17*IFERROR(INDEX(設定!$C$43:$C$45,MATCH(F17,設定!$B$43:$B$45,0)),1)) -> 12 | L17: =IF(B17="","",I17-H17) -> 1500 | M17: =IF(B17="","",IF(H17=0,"",L17/H17)) -> 0.15 | N17: =IF(B17="","",IF(J17=0,"",M17*365/J17)) -> 5.475 | O17: =IF(B17="","",IFERROR(M17/INDEX(設定!$C$43:$C$45,MATCH(F17,設定!$B$43:$B$45,0)),"")) -> 0.125 | P17: =IF(B17="","",IF(J17<=設定!$C$6,IF(M17>=設定!$C$7,"I(コア)","II(回転)"),IF(M17>=設定!$C$7,"III(厳選)","IV(見送り)"))) -> II(回転) | Q17: =IF(B17="","",IF(OR(P17="I(コア)",P17="II(回転)"),"仕入れ候補",IF(P17="III(厳選)","厳選検討（少数）","見送り"))) -> 仕入れ候補
A18: =IF(B18="","",ROW()-12) -> 6 | B18: 一般パック品（遊戯王） | C18: 遊戯王 | D18: C | E18: 下降 | F18: 高 | G18: 3000 | H18: 2800 | I18: 2900 | J18: 90 | K18: =IF(B18="","",J18*IFERROR(INDEX(設定!$C$43:$C$45,MATCH(F18,設定!$B$43:$B$45,0)),1)) -> 135 | L18: =IF(B18="","",I18-H18) -> 100 | M18: =IF(B18="","",IF(H18=0,"",L18/H18)) -> 0.035714286 | N18: =IF(B18="","",IF(J18=0,"",M18*365/J18)) -> 0.14484127 | O18: =IF(B18="","",IFERROR(M18/INDEX(設定!$C$43:$C$45,MATCH(F18,設定!$B$43:$B$45,0)),"")) -> 0.023809524 | P18: =IF(B18="","",IF(J18<=設定!$C$6,IF(M18>=設定!$C$7,"I(コア)","II(回転)"),IF(M18>=設定!$C$7,"III(厳選)","IV(見送り)"))) -> IV(見送り) | Q18: =IF(B18="","",IF(OR(P18="I(コア)",P18="II(回転)"),"仕入れ候補",IF(P18="III(厳選)","厳選検討（少数）","見送り"))) -> 見送り
A19: =IF(B19="","",ROW()-12) | K19: =IF(B19="","",J19*IFERROR(INDEX(設定!$C$43:$C$45,MATCH(F19,設定!$B$43:$B$45,0)),1)) | L19: =IF(B19="","",I19-H19) | M19: =IF(B19="","",IF(H19=0,"",L19/H19)) | N19: =IF(B19="","",IF(J19=0,"",M19*365/J19)) | O19: =IF(B19="","",IFERROR(M19/INDEX(設定!$C$43:$C$45,MATCH(F19,設定!$B$43:$B$45,0)),"")) | P19: =IF(B19="","",IF(J19<=設定!$C$6,IF(M19>=設定!$C$7,"I(コア)","II(回転)"),IF(M19>=設定!$C$7,"III(厳選)","IV(見送り)"))) | Q19: =IF(B19="","",IF(OR(P19="I(コア)",P19="II(回転)"),"仕入れ候補",IF(P19="III(厳選)","厳選検討（少数）","見送り")))
A20: =IF(B20="","",ROW()-12) | K20: =IF(B20="","",J20*IFERROR(INDEX(設定!$C$43:$C$45,MATCH(F20,設定!$B$43:$B$45,0)),1)) | L20: =IF(B20="","",I20-H20) | M20: =IF(B20="","",IF(H20=0,"",L20/H20)) | N20: =IF(B20="","",IF(J20=0,"",M20*365/J20)) | O20: =IF(B20="","",IFERROR(M20/INDEX(設定!$C$43:$C$45,MATCH(F20,設定!$B$43:$B$45,0)),"")) | P20: =IF(B20="","",IF(J20<=設定!$C$6,IF(M20>=設定!$C$7,"I(コア)","II(回転)"),IF(M20>=設定!$C$7,"III(厳選)","IV(見送り)"))) | Q20: =IF(B20="","",IF(OR(P20="I(コア)",P20="II(回転)"),"仕入れ候補",IF(P20="III(厳選)","厳選検討（少数）","見送り")))
A21: =IF(B21="","",ROW()-12) | K21: =IF(B21="","",J21*IFERROR(INDEX(設定!$C$43:$C$45,MATCH(F21,設定!$B$43:$B$45,0)),1)) | L21: =IF(B21="","",I21-H21) | M21: =IF(B21="","",IF(H21=0,"",L21/H21)) | N21: =IF(B21="","",IF(J21=0,"",M21*365/J21)) | O21: =IF(B21="","",IFERROR(M21/INDEX(設定!$C$43:$C$45,MATCH(F21,設定!$B$43:$B$45,0)),"")) | P21: =IF(B21="","",IF(J21<=設定!$C$6,IF(M21>=設定!$C$7,"I(コア)","II(回転)"),IF(M21>=設定!$C$7,"III(厳選)","IV(見送り)"))) | Q21: =IF(B21="","",IF(OR(P21="I(コア)",P21="II(回転)"),"仕入れ候補",IF(P21="III(厳選)","厳選検討（少数）","見送り")))
A22: =IF(B22="","",ROW()-12) | K22: =IF(B22="","",J22*IFERROR(INDEX(設定!$C$43:$C$45,MATCH(F22,設定!$B$43:$B$45,0)),1)) | L22: =IF(B22="","",I22-H22) | M22: =IF(B22="","",IF(H22=0,"",L22/H22)) | N22: =IF(B22="","",IF(J22=0,"",M22*365/J22)) | O22: =IF(B22="","",IFERROR(M22/INDEX(設定!$C$43:$C$45,MATCH(F22,設定!$B$43:$B$45,0)),"")) | P22: =IF(B22="","",IF(J22<=設定!$C$6,IF(M22>=設定!$C$7,"I(コア)","II(回転)"),IF(M22>=設定!$C$7,"III(厳選)","IV(見送り)"))) | Q22: =IF(B22="","",IF(OR(P22="I(コア)",P22="II(回転)"),"仕入れ候補",IF(P22="III(厳選)","厳選検討（少数）","見送り")))
A23: =IF(B23="","",ROW()-12) | K23: =IF(B23="","",J23*IFERROR(INDEX(設定!$C$43:$C$45,MATCH(F23,設定!$B$43:$B$45,0)),1)) | L23: =IF(B23="","",I23-H23) | M23: =IF(B23="","",IF(H23=0,"",L23/H23)) | N23: =IF(B23="","",IF(J23=0,"",M23*365/J23)) | O23: =IF(B23="","",IFERROR(M23/INDEX(設定!$C$43:$C$45,MATCH(F23,設定!$B$43:$B$45,0)),"")) | P23: =IF(B23="","",IF(J23<=設定!$C$6,IF(M23>=設定!$C$7,"I(コア)","II(回転)"),IF(M23>=設定!$C$7,"III(厳選)","IV(見送り)"))) | Q23: =IF(B23="","",IF(OR(P23="I(コア)",P23="II(回転)"),"仕入れ候補",IF(P23="III(厳選)","厳選検討（少数）","見送り")))
A24: =IF(B24="","",ROW()-12) | K24: =IF(B24="","",J24*IFERROR(INDEX(設定!$C$43:$C$45,MATCH(F24,設定!$B$43:$B$45,0)),1)) | L24: =IF(B24="","",I24-H24) | M24: =IF(B24="","",IF(H24=0,"",L24/H24)) | N24: =IF(B24="","",IF(J24=0,"",M24*365/J24)) | O24: =IF(B24="","",IFERROR(M24/INDEX(設定!$C$43:$C$45,MATCH(F24,設定!$B$43:$B$45,0)),"")) | P24: =IF(B24="","",IF(J24<=設定!$C$6,IF(M24>=設定!$C$7,"I(コア)","II(回転)"),IF(M24>=設定!$C$7,"III(厳選)","IV(見送り)"))) | Q24: =IF(B24="","",IF(OR(P24="I(コア)",P24="II(回転)"),"仕入れ候補",IF(P24="III(厳選)","厳選検討（少数）","見送り")))
A25: =IF(B25="","",ROW()-12) | K25: =IF(B25="","",J25*IFERROR(INDEX(設定!$C$43:$C$45,MATCH(F25,設定!$B$43:$B$45,0)),1)) | L25: =IF(B25="","",I25-H25) | M25: =IF(B25="","",IF(H25=0,"",L25/H25)) | N25: =IF(B25="","",IF(J25=0,"",M25*365/J25)) | O25: =IF(B25="","",IFERROR(M25/INDEX(設定!$C$43:$C$45,MATCH(F25,設定!$B$43:$B$45,0)),"")) | P25: =IF(B25="","",IF(J25<=設定!$C$6,IF(M25>=設定!$C$7,"I(コア)","II(回転)"),IF(M25>=設定!$C$7,"III(厳選)","IV(見送り)"))) | Q25: =IF(B25="","",IF(OR(P25="I(コア)",P25="II(回転)"),"仕入れ候補",IF(P25="III(厳選)","厳選検討（少数）","見送り")))
A26: =IF(B26="","",ROW()-12) | K26: =IF(B26="","",J26*IFERROR(INDEX(設定!$C$43:$C$45,MATCH(F26,設定!$B$43:$B$45,0)),1)) | L26: =IF(B26="","",I26-H26) | M26: =IF(B26="","",IF(H26=0,"",L26/H26)) | N26: =IF(B26="","",IF(J26=0,"",M26*365/J26)) | O26: =IF(B26="","",IFERROR(M26/INDEX(設定!$C$43:$C$45,MATCH(F26,設定!$B$43:$B$45,0)),"")) | P26: =IF(B26="","",IF(J26<=設定!$C$6,IF(M26>=設定!$C$7,"I(コア)","II(回転)"),IF(M26>=設定!$C$7,"III(厳選)","IV(見送り)"))) | Q26: =IF(B26="","",IF(OR(P26="I(コア)",P26="II(回転)"),"仕入れ候補",IF(P26="III(厳選)","厳選検討（少数）","見送り")))
A27: =IF(B27="","",ROW()-12) | K27: =IF(B27="","",J27*IFERROR(INDEX(設定!$C$43:$C$45,MATCH(F27,設定!$B$43:$B$45,0)),1)) | L27: =IF(B27="","",I27-H27) | M27: =IF(B27="","",IF(H27=0,"",L27/H27)) | N27: =IF(B27="","",IF(J27=0,"",M27*365/J27)) | O27: =IF(B27="","",IFERROR(M27/INDEX(設定!$C$43:$C$45,MATCH(F27,設定!$B$43:$B$45,0)),"")) | P27: =IF(B27="","",IF(J27<=設定!$C$6,IF(M27>=設定!$C$7,"I(コア)","II(回転)"),IF(M27>=設定!$C$7,"III(厳選)","IV(見送り)"))) | Q27: =IF(B27="","",IF(OR(P27="I(コア)",P27="II(回転)"),"仕入れ候補",IF(P27="III(厳選)","厳選検討（少数）","見送り")))
A28: =IF(B28="","",ROW()-12) | K28: =IF(B28="","",J28*IFERROR(INDEX(設定!$C$43:$C$45,MATCH(F28,設定!$B$43:$B$45,0)),1)) | L28: =IF(B28="","",I28-H28) | M28: =IF(B28="","",IF(H28=0,"",L28/H28)) | N28: =IF(B28="","",IF(J28=0,"",M28*365/J28)) | O28: =IF(B28="","",IFERROR(M28/INDEX(設定!$C$43:$C$45,MATCH(F28,設定!$B$43:$B$45,0)),"")) | P28: =IF(B28="","",IF(J28<=設定!$C$6,IF(M28>=設定!$C$7,"I(コア)","II(回転)"),IF(M28>=設定!$C$7,"III(厳選)","IV(見送り)"))) | Q28: =IF(B28="","",IF(OR(P28="I(コア)",P28="II(回転)"),"仕入れ候補",IF(P28="III(厳選)","厳選検討（少数）","見送り")))
A29: =IF(B29="","",ROW()-12) | K29: =IF(B29="","",J29*IFERROR(INDEX(設定!$C$43:$C$45,MATCH(F29,設定!$B$43:$B$45,0)),1)) | L29: =IF(B29="","",I29-H29) | M29: =IF(B29="","",IF(H29=0,"",L29/H29)) | N29: =IF(B29="","",IF(J29=0,"",M29*365/J29)) | O29: =IF(B29="","",IFERROR(M29/INDEX(設定!$C$43:$C$45,MATCH(F29,設定!$B$43:$B$45,0)),"")) | P29: =IF(B29="","",IF(J29<=設定!$C$6,IF(M29>=設定!$C$7,"I(コア)","II(回転)"),IF(M29>=設定!$C$7,"III(厳選)","IV(見送り)"))) | Q29: =IF(B29="","",IF(OR(P29="I(コア)",P29="II(回転)"),"仕入れ候補",IF(P29="III(厳選)","厳選検討（少数）","見送り")))
A30: =IF(B30="","",ROW()-12) | K30: =IF(B30="","",J30*IFERROR(INDEX(設定!$C$43:$C$45,MATCH(F30,設定!$B$43:$B$45,0)),1)) | L30: =IF(B30="","",I30-H30) | M30: =IF(B30="","",IF(H30=0,"",L30/H30)) | N30: =IF(B30="","",IF(J30=0,"",M30*365/J30)) | O30: =IF(B30="","",IFERROR(M30/INDEX(設定!$C$43:$C$45,MATCH(F30,設定!$B$43:$B$45,0)),"")) | P30: =IF(B30="","",IF(J30<=設定!$C$6,IF(M30>=設定!$C$7,"I(コア)","II(回転)"),IF(M30>=設定!$C$7,"III(厳選)","IV(見送り)"))) | Q30: =IF(B30="","",IF(OR(P30="I(コア)",P30="II(回転)"),"仕入れ候補",IF(P30="III(厳選)","厳選検討（少数）","見送り")))
... A112: =IF(B112="","",ROW()-12) | K112: =IF(B112="","",J112*IFERROR(INDEX(設定!$C$43:$C$45,MATCH(F112,設定!$B$43:$B$45,0)),1)) | L112: =IF(B112="","",I112-H112) | M112: =IF(B112="","",IF(H112=0,"",L112/H112)) | N112: =IF(B112="","",IF(J112=0,"",M112*365/J112)) | O112: =IF(B112="","",IFERROR(M112/INDEX(設定!$C$43:$C$45,MATCH(F112,設定!$B$43:$B$45,0)),"")) | P112: =IF(B112="","",IF(J112<=設定!$C$6,IF(M112>=設定!$C$7,"I(コア)","II(回転)"),IF(M112>=設定!$C$7,"III(厳選)","IV(見送り)"))) | Q112: =IF(B112="","",IF(OR(P112="I(コア)",P112="II(回転)"),"仕入れ候補",IF(P112="III(厳選)","厳選検討（少数）","見送り")))

Sheet 仕入れ計画
B2: 仕入れ計画（象限別ルール）
B3: 「何を・いくらまで・どの希少性／トレンド／ボラティリティなら仕入れてよいか」を象限ごとに定義し、月間予算を配分します。黄色セルが判断の起点です。
B5: 月間仕入れ総予算 | C5: 500000
A7: 象限 | B7: 呼称 | C7: 方針 | D7: 対象タイトル例 | E7: 上限仕入単価 | F7: 許容希少性 | G7: 許容トレンド | H7: 許容ボラティリティ | I7: 予算配分比率 | J7: 予算配分金額 | K7: 在庫上限点数 | L7: ウォッチ候補数 | M7: 現在庫点数
A8: I(コア) | B8: I(コア) | C8: 積極的に仕入れる中心銘柄。優先確保。 | D8: ポケモンカード、ワンピースカード | E8: 50000 | F8: S以上 | G8: 上昇 | H8: 低〜中 | I8: 0.55 | J8: =$C$5*I8 -> 275000 | K8: 15 | L8: =COUNTIF(ウォッチリスト!$P$13:$P$112,"I(コア)") -> 2 | M8: =COUNTIF(在庫管理!$V$11:$V$110,"I(コア)") -> 1
A9: II(回転) | B9: II(回転) | C9: 資金回転重視。数量で稼ぐ。 | D9: 遊戯王、デュエル・マスターズ | E9: 15000 | F9: A以上 | G9: 上昇・安定 | H9: 指定なし | I9: 0.2 | J9: =$C$5*I9 -> 100000 | K9: 40 | L9: =COUNTIF(ウォッチリスト!$P$13:$P$112,"II(回転)") -> 1 | M9: =COUNTIF(在庫管理!$V$11:$V$110,"II(回転)") -> 1
A10: III(厳選) | B10: III(厳選) | C10: 少数厳選。資金拘束を許容できる範囲で。 | D10: ポケモンカード、ワンピースカード | E10: 80000 | F10: SS | G10: 上昇・安定 | H10: 低 | I10: 0.2 | J10: =$C$5*I10 -> 100000 | K10: 5 | L10: =COUNTIF(ウォッチリスト!$P$13:$P$112,"III(厳選)") -> 2 | M10: =COUNTIF(在庫管理!$V$11:$V$110,"III(厳選)") -> 1
A11: IV(見送り) | B11: IV(見送り) | C11: 原則仕入れ見送り。ウォッチのみ継続。 | D11: - | E11: 0 | F11: - | G11: 下降 | H11: 高 | I11: 0.05 | J11: =$C$5*I11 -> 25000 | K11: 0 | L11: =COUNTIF(ウォッチリスト!$P$13:$P$112,"IV(見送り)") -> 1 | M11: =COUNTIF(在庫管理!$V$11:$V$110,"IV(見送り)") -> 2
B12: 合計 | I12: =SUM(I8:I11) -> 1 | J12: =SUM(J8:J11) -> 500000
B14: ※ 予算配分比率の合計は100%になるように調整してください（赤色表示は100%以外を意味します）。
B15: ※ 許容希少性／許容トレンド／許容ボラティリティは、ウォッチリスト・在庫管理シートの各カードの値と見比べて仕入れ可否を判断するための基準です。
B16: ※ 予算配分の初期値（55%/20%/20%/5%）はコア・サテライト型投資の考え方（コアが過半・劣後は最小限）を参考にした値です。同じ象限内でカードを選ぶ際は、ウォッチリスト・在庫管理シートの「資本効率」が高いものを優先し、「ポジションサイズ目安」が低いもの（＝ボラティリティが高いもの）は保有量を絞ってください。

Sheet 在庫管理
B2: 在庫管理シート（実在庫・ポートフォリオ管理）
B3: 青字セルのみ入力してください。ステータスが「在庫中」の行のみ、集計・ポートフォリオ比率に反映されます。
B5: 総仕入額（在庫中） | C5: =SUMIFS(N11:N110,L11:L110,"在庫中") -> 78000
B6: 総時価（在庫中） | C6: =SUMIFS(O11:O110,L11:L110,"在庫中") -> 98500
B7: 含み損益 | C7: =C6-C5 -> 20500
B8: 含み損益率 | C8: =IFERROR(C7/C5,"") -> 0.26282051
B9: 在庫点数（在庫中） | C9: =COUNTIF(L11:L110,"在庫中") -> 3
A10: No | B10: 商品名 | C10: 銘柄タイトル | D10: キャラ | E10: イラストレーター | F10: 企画・収録弾 （相関ドライバー） | G10: 絶版 | H10: 周年 | I10: 希少性 | J10: トレンド | K10: ボラティリティ | L10: ステータス | M10: 仕入日 | N10: 仕入値 | O10: 現在時価 （想定売却価格） | P10: 想定売却 日数 | Q10: 実効想定売却 日数（ボラ考慮） | R10: 想定粗利額 | S10: 想定粗利率 | T10: 資本効率 （利益率×回転率） | U10: ポジション サイズ目安 | V10: 象限 | W10: ポートフォリオ 比率 | X10: メモ
A11: =IF(B11="","",ROW()-10) -> 1 | B11: リザードンVMAX（ポケモンカード） | C11: ポケモンカード | D11: リザードン | E11: サンプル絵師A | F11: スカーレット&バイオレット 151 | G11: × | H11: × | I11: SS | J11: 上昇 | K11: 低 | L11: 在庫中 | M11: 2026-06-15 | N11: 24000 | O11: 31000 | P11: 18 | Q11: =IF(B11="","",P11*IFERROR(INDEX(設定!$C$43:$C$45,MATCH(K11,設定!$B$43:$B$45,0)),1)) -> 18 | R11: =IF(B11="","",O11-N11) -> 7000 | S11: =IF(B11="","",IF(N11=0,"",R11/N11)) -> 0.29166667 | T11: =IF(B11="","",IF(P11=0,"",S11*365/P11)) -> 5.9143519 | U11: =IF(B11="","",IFERROR(S11/INDEX(設定!$C$43:$C$45,MATCH(K11,設定!$B$43:$B$45,0)),"")) -> 0.29166667 | V11: =IF(B11="","",IF(P11<=設定!$C$6,IF(S11>=設定!$C$7,"I(コア)","II(回転)"),IF(S11>=設定!$C$7,"III(厳選)","IV(見送り)"))) -> I(コア) | W11: =IF(B11="","",IF(L11="在庫中",IF($C$6=0,"",O11/$C$6),"")) -> 0.31472081
A12: =IF(B12="","",ROW()-10) -> 2 | B12: ルフィ SEC（ワンピースカード） | C12: ワンピースカード | D12: ルフィ | F12: ROMANCE DAWN | G12: × | H12: × | I12: S | J12: 上昇 | K12: 中 | L12: 在庫中 | M12: 2026-07-01 | N12: 16000 | O12: 18500 | P12: 12 | Q12: =IF(B12="","",P12*IFERROR(INDEX(設定!$C$43:$C$45,MATCH(K12,設定!$B$43:$B$45,0)),1)) -> 14.4 | R12: =IF(B12="","",O12-N12) -> 2500 | S12: =IF(B12="","",IF(N12=0,"",R12/N12)) -> 0.15625 | T12: =IF(B12="","",IF(P12=0,"",S12*365/P12)) -> 4.7526042 | U12: =IF(B12="","",IFERROR(S12/INDEX(設定!$C$43:$C$45,MATCH(K12,設定!$B$43:$B$45,0)),"")) -> 0.13020833 | V12: =IF(B12="","",IF(P12<=設定!$C$6,IF(S12>=設定!$C$7,"I(コア)","II(回転)"),IF(S12>=設定!$C$7,"III(厳選)","IV(見送り)"))) -> II(回転) | W12: =IF(B12="","",IF(L12="在庫中",IF($C$6=0,"",O12/$C$6),"")) -> 0.18781726
A13: =IF(B13="","",ROW()-10) -> 3 | B13: 青眼の白龍 初期（遊戯王） | C13: 遊戯王 | D13: 青眼の白龍 | F13: 初期弾 | G13: ○ | H13: × | I13: SS | J13: 安定 | K13: 低 | L13: 在庫中 | M13: 2026-05-20 | N13: 38000 | O13: 49000 | P13: 55 | Q13: =IF(B13="","",P13*IFERROR(INDEX(設定!$C$43:$C$45,MATCH(K13,設定!$B$43:$B$45,0)),1)) -> 55 | R13: =IF(B13="","",O13-N13) -> 11000 | S13: =IF(B13="","",IF(N13=0,"",R13/N13)) -> 0.28947368 | T13: =IF(B13="","",IF(P13=0,"",S13*365/P13)) -> 1.9210526 | U13: =IF(B13="","",IFERROR(S13/INDEX(設定!$C$43:$C$45,MATCH(K13,設定!$B$43:$B$45,0)),"")) -> 0.28947368 | V13: =IF(B13="","",IF(P13<=設定!$C$6,IF(S13>=設定!$C$7,"I(コア)","II(回転)"),IF(S13>=設定!$C$7,"III(厳選)","IV(見送り)"))) -> III(厳選) | W13: =IF(B13="","",IF(L13="在庫中",IF($C$6=0,"",O13/$C$6),"")) -> 0.49746193 | X13: 絶版・入手困難
A14: =IF(B14="","",ROW()-10) -> 4 | B14: ピカチュウ プロモ（ポケモンカード） | C14: ポケモンカード | D14: ピカチュウ | E14: サンプル絵師B | F14: 25周年記念 | G14: × | H14: ○ | I14: A | J14: 安定 | K14: 中 | L14: 受注済 | M14: 2026-07-10 | N14: 7000 | O14: 8300 | P14: 40 | Q14: =IF(B14="","",P14*IFERROR(INDEX(設定!$C$43:$C$45,MATCH(K14,設定!$B$43:$B$45,0)),1)) -> 48 | R14: =IF(B14="","",O14-N14) -> 1300 | S14: =IF(B14="","",IF(N14=0,"",R14/N14)) -> 0.18571429 | T14: =IF(B14="","",IF(P14=0,"",S14*365/P14)) -> 1.6946429 | U14: =IF(B14="","",IFERROR(S14/INDEX(設定!$C$43:$C$45,MATCH(K14,設定!$B$43:$B$45,0)),"")) -> 0.1547619 | V14: =IF(B14="","",IF(P14<=設定!$C$6,IF(S14>=設定!$C$7,"I(コア)","II(回転)"),IF(S14>=設定!$C$7,"III(厳選)","IV(見送り)"))) -> IV(見送り) | W14: =IF(B14="","",IF(L14="在庫中",IF($C$6=0,"",O14/$C$6),"")) | X14: 周年記念
A15: =IF(B15="","",ROW()-10) -> 5 | B15: 一般パック品（遊戯王） | C15: 遊戯王 | G15: × | H15: × | I15: C | J15: 下降 | K15: 高 | L15: 売却済 | M15: 2026-04-01 | N15: 2800 | O15: 2900 | P15: 90 | Q15: =IF(B15="","",P15*IFERROR(INDEX(設定!$C$43:$C$45,MATCH(K15,設定!$B$43:$B$45,0)),1)) -> 135 | R15: =IF(B15="","",O15-N15) -> 100 | S15: =IF(B15="","",IF(N15=0,"",R15/N15)) -> 0.035714286 | T15: =IF(B15="","",IF(P15=0,"",S15*365/P15)) -> 0.14484127 | U15: =IF(B15="","",IFERROR(S15/INDEX(設定!$C$43:$C$45,MATCH(K15,設定!$B$43:$B$45,0)),"")) -> 0.023809524 | V15: =IF(B15="","",IF(P15<=設定!$C$6,IF(S15>=設定!$C$7,"I(コア)","II(回転)"),IF(S15>=設定!$C$7,"III(厳選)","IV(見送り)"))) -> IV(見送り) | W15: =IF(B15="","",IF(L15="在庫中",IF($C$6=0,"",O15/$C$6),""))
A16: =IF(B16="","",ROW()-10) | Q16: =IF(B16="","",P16*IFERROR(INDEX(設定!$C$43:$C$45,MATCH(K16,設定!$B$43:$B$45,0)),1)) | R16: =IF(B16="","",O16-N16) | S16: =IF(B16="","",IF(N16=0,"",R16/N16)) | T16: =IF(B16="","",IF(P16=0,"",S16*365/P16)) | U16: =IF(B16="","",IFERROR(S16/INDEX(設定!$C$43:$C$45,MATCH(K16,設定!$B$43:$B$45,0)),"")) | V16: =IF(B16="","",IF(P16<=設定!$C$6,IF(S16>=設定!$C$7,"I(コア)","II(回転)"),IF(S16>=設定!$C$7,"III(厳選)","IV(見送り)"))) | W16: =IF(B16="","",IF(L16="在庫中",IF($C$6=0,"",O16/$C$6),""))
A17: =IF(B17="","",ROW()-10) | Q17: =IF(B17="","",P17*IFERROR(INDEX(設定!$C$43:$C$45,MATCH(K17,設定!$B$43:$B$45,0)),1)) | R17: =IF(B17="","",O17-N17) | S17: =IF(B17="","",IF(N17=0,"",R17/N17)) | T17: =IF(B17="","",IF(P17=0,"",S17*365/P17)) | U17: =IF(B17="","",IFERROR(S17/INDEX(設定!$C$43:$C$45,MATCH(K17,設定!$B$43:$B$45,0)),"")) | V17: =IF(B17="","",IF(P17<=設定!$C$6,IF(S17>=設定!$C$7,"I(コア)","II(回転)"),IF(S17>=設定!$C$7,"III(厳選)","IV(見送り)"))) | W17: =IF(B17="","",IF(L17="在庫中",IF($C$6=0,"",O17/$C$6),""))
A18: =IF(B18="","",ROW()-10) | Q18: =IF(B18="","",P18*IFERROR(INDEX(設定!$C$43:$C$45,MATCH(K18,設定!$B$43:$B$45,0)),1)) | R18: =IF(B18="","",O18-N18) | S18: =IF(B18="","",IF(N18=0,"",R18/N18)) | T18: =IF(B18="","",IF(P18=0,"",S18*365/P18)) | U18: =IF(B18="","",IFERROR(S18/INDEX(設定!$C$43:$C$45,MATCH(K18,設定!$B$43:$B$45,0)),"")) | V18: =IF(B18="","",IF(P18<=設定!$C$6,IF(S18>=設定!$C$7,"I(コア)","II(回転)"),IF(S18>=設定!$C$7,"III(厳選)","IV(見送り)"))) | W18: =IF(B18="","",IF(L18="在庫中",IF($C$6=0,"",O18/$C$6),""))
A19: =IF(B19="","",ROW()-10) | Q19: =IF(B19="","",P19*IFERROR(INDEX(設定!$C$43:$C$45,MATCH(K19,設定!$B$43:$B$45,0)),1)) | R19: =IF(B19="","",O19-N19) | S19: =IF(B19="","",IF(N19=0,"",R19/N19)) | T19: =IF(B19="","",IF(P19=0,"",S19*365/P19)) | U19: =IF(B19="","",IFERROR(S19/INDEX(設定!$C$43:$C$45,MATCH(K19,設定!$B$43:$B$45,0)),"")) | V19: =IF(B19="","",IF(P19<=設定!$C$6,IF(S19>=設定!$C$7,"I(コア)","II(回転)"),IF(S19>=設定!$C$7,"III(厳選)","IV(見送り)"))) | W19: =IF(B19="","",IF(L19="在庫中",IF($C$6=0,"",O19/$C$6),""))
A20: =IF(B20="","",ROW()-10) | Q20: =IF(B20="","",P20*IFERROR(INDEX(設定!$C$43:$C$45,MATCH(K20,設定!$B$43:$B$45,0)),1)) | R20: =IF(B20="","",O20-N20) | S20: =IF(B20="","",IF(N20=0,"",R20/N20)) | T20: =IF(B20="","",IF(P20=0,"",S20*365/P20)) | U20: =IF(B20="","",IFERROR(S20/INDEX(設定!$C$43:$C$45,MATCH(K20,設定!$B$43:$B$45,0)),"")) | V20: =IF(B20="","",IF(P20<=設定!$C$6,IF(S20>=設定!$C$7,"I(コア)","II(回転)"),IF(S20>=設定!$C$7,"III(厳選)","IV(見送り)"))) | W20: =IF(B20="","",IF(L20="在庫中",IF($C$6=0,"",O20/$C$6),""))
A21: =IF(B21="","",ROW()-10) | Q21: =IF(B21="","",P21*IFERROR(INDEX(設定!$C$43:$C$45,MATCH(K21,設定!$B$43:$B$45,0)),1)) | R21: =IF(B21="","",O21-N21) | S21: =IF(B21="","",IF(N21=0,"",R21/N21)) | T21: =IF(B21="","",IF(P21=0,"",S21*365/P21)) | U21: =IF(B21="","",IFERROR(S21/INDEX(設定!$C$43:$C$45,MATCH(K21,設定!$B$43:$B$45,0)),"")) | V21: =IF(B21="","",IF(P21<=設定!$C$6,IF(S21>=設定!$C$7,"I(コア)","II(回転)"),IF(S21>=設定!$C$7,"III(厳選)","IV(見送り)"))) | W21: =IF(B21="","",IF(L21="在庫中",IF($C$6=0,"",O21/$C$6),""))
A22: =IF(B22="","",ROW()-10) | Q22: =IF(B22="","",P22*IFERROR(INDEX(設定!$C$43:$C$45,MATCH(K22,設定!$B$43:$B$45,0)),1)) | R22: =IF(B22="","",O22-N22) | S22: =IF(B22="","",IF(N22=0,"",R22/N22)) | T22: =IF(B22="","",IF(P22=0,"",S22*365/P22)) | U22: =IF(B22="","",IFERROR(S22/INDEX(設定!$C$43:$C$45,MATCH(K22,設定!$B$43:$B$45,0)),"")) | V22: =IF(B22="","",IF(P22<=設定!$C$6,IF(S22>=設定!$C$7,"I(コア)","II(回転)"),IF(S22>=設定!$C$7,"III(厳選)","IV(見送り)"))) | W22: =IF(B22="","",IF(L22="在庫中",IF($C$6=0,"",O22/$C$6),""))
A23: =IF(B23="","",ROW()-10) | Q23: =IF(B23="","",P23*IFERROR(INDEX(設定!$C$43:$C$45,MATCH(K23,設定!$B$43:$B$45,0)),1)) | R23: =IF(B23="","",O23-N23) | S23: =IF(B23="","",IF(N23=0,"",R23/N23)) | T23: =IF(B23="","",IF(P23=0,"",S23*365/P23)) | U23: =IF(B23="","",IFERROR(S23/INDEX(設定!$C$43:$C$45,MATCH(K23,設定!$B$43:$B$45,0)),"")) | V23: =IF(B23="","",IF(P23<=設定!$C$6,IF(S23>=設定!$C$7,"I(コア)","II(回転)"),IF(S23>=設定!$C$7,"III(厳選)","IV(見送り)"))) | W23: =IF(B23="","",IF(L23="在庫中",IF($C$6=0,"",O23/$C$6),""))
A24: =IF(B24="","",ROW()-10) | Q24: =IF(B24="","",P24*IFERROR(INDEX(設定!$C$43:$C$45,MATCH(K24,設定!$B$43:$B$45,0)),1)) | R24: =IF(B24="","",O24-N24) | S24: =IF(B24="","",IF(N24=0,"",R24/N24)) | T24: =IF(B24="","",IF(P24=0,"",S24*365/P24)) | U24: =IF(B24="","",IFERROR(S24/INDEX(設定!$C$43:$C$45,MATCH(K24,設定!$B$43:$B$45,0)),"")) | V24: =IF(B24="","",IF(P24<=設定!$C$6,IF(S24>=設定!$C$7,"I(コア)","II(回転)"),IF(S24>=設定!$C$7,"III(厳選)","IV(見送り)"))) | W24: =IF(B24="","",IF(L24="在庫中",IF($C$6=0,"",O24/$C$6),""))
A25: =IF(B25="","",ROW()-10) | Q25: =IF(B25="","",P25*IFERROR(INDEX(設定!$C$43:$C$45,MATCH(K25,設定!$B$43:$B$45,0)),1)) | R25: =IF(B25="","",O25-N25) | S25: =IF(B25="","",IF(N25=0,"",R25/N25)) | T25: =IF(B25="","",IF(P25=0,"",S25*365/P25)) | U25: =IF(B25="","",IFERROR(S25/INDEX(設定!$C$43:$C$45,MATCH(K25,設定!$B$43:$B$45,0)),"")) | V25: =IF(B25="","",IF(P25<=設定!$C$6,IF(S25>=設定!$C$7,"I(コア)","II(回転)"),IF(S25>=設定!$C$7,"III(厳選)","IV(見送り)"))) | W25: =IF(B25="","",IF(L25="在庫中",IF($C$6=0,"",O25/$C$6),""))
A26: =IF(B26="","",ROW()-10) | Q26: =IF(B26="","",P26*IFERROR(INDEX(設定!$C$43:$C$45,MATCH(K26,設定!$B$43:$B$45,0)),1)) | R26: =IF(B26="","",O26-N26) | S26: =IF(B26="","",IF(N26=0,"",R26/N26)) | T26: =IF(B26="","",IF(P26=0,"",S26*365/P26)) | U26: =IF(B26="","",IFERROR(S26/INDEX(設定!$C$43:$C$45,MATCH(K26,設定!$B$43:$B$45,0)),"")) | V26: =IF(B26="","",IF(P26<=設定!$C$6,IF(S26>=設定!$C$7,"I(コア)","II(回転)"),IF(S26>=設定!$C$7,"III(厳選)","IV(見送り)"))) | W26: =IF(B26="","",IF(L26="在庫中",IF($C$6=0,"",O26/$C$6),""))
A27: =IF(B27="","",ROW()-10) | Q27: =IF(B27="","",P27*IFERROR(INDEX(設定!$C$43:$C$45,MATCH(K27,設定!$B$43:$B$45,0)),1)) | R27: =IF(B27="","",O27-N27) | S27: =IF(B27="","",IF(N27=0,"",R27/N27)) | T27: =IF(B27="","",IF(P27=0,"",S27*365/P27)) | U27: =IF(B27="","",IFERROR(S27/INDEX(設定!$C$43:$C$45,MATCH(K27,設定!$B$43:$B$45,0)),"")) | V27: =IF(B27="","",IF(P27<=設定!$C$6,IF(S27>=設定!$C$7,"I(コア)","II(回転)"),IF(S27>=設定!$C$7,"III(厳選)","IV(見送り)"))) | W27: =IF(B27="","",IF(L27="在庫中",IF($C$6=0,"",O27/$C$6),""))
... A110: =IF(B110="","",ROW()-10) | Q110: =IF(B110="","",P110*IFERROR(INDEX(設定!$C$43:$C$45,MATCH(K110,設定!$B$43:$B$45,0)),1)) | R110: =IF(B110="","",O110-N110) | S110: =IF(B110="","",IF(N110=0,"",R110/N110)) | T110: =IF(B110="","",IF(P110=0,"",S110*365/P110)) | U110: =IF(B110="","",IFERROR(S110/INDEX(設定!$C$43:$C$45,MATCH(K110,設定!$B$43:$B$45,0)),"")) | V110: =IF(B110="","",IF(P110<=設定!$C$6,IF(S110>=設定!$C$7,"I(コア)","II(回転)"),IF(S110>=設定!$C$7,"III(厳選)","IV(見送り)"))) | W110: =IF(B110="","",IF(L110="在庫中",IF($C$6=0,"",O110/$C$6),""))

Sheet ダッシュボード
B2: ダッシュボード
B3: 在庫管理シートを自動集計します。手入力は不要です（すべて数式）。
B5: ■ 資金効率
B6: 総仕入額（在庫中） | C6: =在庫管理!$C$5 -> 78000
B7: 総時価（在庫中） | C7: =在庫管理!$C$6 -> 98500
B8: 含み損益 | C8: =在庫管理!$C$7 -> 20500
B9: 含み損益率 | C9: =在庫管理!$C$8 -> 0.26282051
B10: 資金倍率（時価 ÷ 仕入額） | C10: =IFERROR($C$7/$C$6,"") -> 1.2628205
B11: 平均想定売却日数（時価加重） | C11: =IFERROR(SUMPRODUCT((在庫管理!$L$11:$L$110="在庫中")*在庫管理!$P$11:$P$110*在庫管理!$O$11:$O$110)/$C$7,"") -> 35.279188
B12: 在庫の入れ替わり回数（年間・365日÷平均売却日数） | C12: =IFERROR(365/$C$11,"") -> 10.346043
B14: ■ 換金のしやすさ
B15: 早く売れる基準以内の在庫比率（時価ベース） | C15: =IFERROR(SUMIFS(在庫管理!$O$11:$O$110,在庫管理!$L$11:$L$110,"在庫中",在庫管理!$P$11:$P$110,"<="&設定!$C$6)/$C$7,"") -> 0.50253807
B16: 売れ残りリスクが高い在庫比率（時価ベース） | C16: =IFERROR(SUMIFS(在庫管理!$O$11:$O$110,在庫管理!$L$11:$L$110,"在庫中",在庫管理!$P$11:$P$110,">"&設定!$C$8)/$C$7,"") -> 0
B17: 回転が速い在庫比率（コア＋回転、時価ベース） | C17: =IFERROR((SUMIFS(在庫管理!$O$11:$O$110,在庫管理!$L$11:$L$110,"在庫中",在庫管理!$V$11:$V$110,"I(コア)")+SUMIFS(在庫管理!$O$11:$O$110,在庫管理!$L$11:$L$110,"在庫中",在庫管理!$V$11:$V$110,"II(回転)"))/$C$7,"") -> 0.50253807
B18: 回転が遅い在庫比率（厳選＋見送り、時価ベース） | C18: =IFERROR((SUMIFS(在庫管理!$O$11:$O$110,在庫管理!$L$11:$L$110,"在庫中",在庫管理!$V$11:$V$110,"III(厳選)")+SUMIFS(在庫管理!$O$11:$O$110,在庫管理!$L$11:$L$110,"在庫中",在庫管理!$V$11:$V$110,"IV(見送り)"))/$C$7,"") -> 0.49746193
B20: ■ 偏りリスク分析（特定の銘柄・カテゴリに偏っていないかを確認。数値が大きいほど偏りが大きい。目安：1,500未満=分散／1,500〜2,500=中程度／2,500以上=偏りが大きい）
B22: 銘柄タイトル | C22: 時価（在庫中） | D22: 構成比 | E22: 偏りスコア | G22: 象限 | H22: 時価（在庫中） | I22: 構成比 | J22: 偏りスコア
B23: =設定!B20 -> ポケモンカード | C23: =SUMIFS(在庫管理!$O$11:$O$110,在庫管理!$L$11:$L$110,"在庫中",在庫管理!$C$11:$C$110,$B23) -> 31000 | D23: =IFERROR($C23/$C$7,"") -> 0.31472081 | E23: =IFERROR($D23^2*10000,0) -> 990.4919 | G23: I(コア) | H23: =SUMIFS(在庫管理!$O$11:$O$110,在庫管理!$L$11:$L$110,"在庫中",在庫管理!$V$11:$V$110,$G23) -> 31000 | I23: =IFERROR($H23/$C$7,"") -> 0.31472081 | J23: =IFERROR($I23^2*10000,0) -> 990.4919
B24: =設定!B21 -> ワンピースカード | C24: =SUMIFS(在庫管理!$O$11:$O$110,在庫管理!$L$11:$L$110,"在庫中",在庫管理!$C$11:$C$110,$B24) -> 18500 | D24: =IFERROR($C24/$C$7,"") -> 0.18781726 | E24: =IFERROR($D24^2*10000,0) -> 352.75323 | G24: II(回転) | H24: =SUMIFS(在庫管理!$O$11:$O$110,在庫管理!$L$11:$L$110,"在庫中",在庫管理!$V$11:$V$110,$G24) -> 18500 | I24: =IFERROR($H24/$C$7,"") -> 0.18781726 | J24: =IFERROR($I24^2*10000,0) -> 352.75323
B25: =設定!B22 -> 遊戯王 | C25: =SUMIFS(在庫管理!$O$11:$O$110,在庫管理!$L$11:$L$110,"在庫中",在庫管理!$C$11:$C$110,$B25) -> 49000 | D25: =IFERROR($C25/$C$7,"") -> 0.49746193 | E25: =IFERROR($D25^2*10000,0) -> 2474.6837 | G25: III(厳選) | H25: =SUMIFS(在庫管理!$O$11:$O$110,在庫管理!$L$11:$L$110,"在庫中",在庫管理!$V$11:$V$110,$G25) -> 49000 | I25: =IFERROR($H25/$C$7,"") -> 0.49746193 | J25: =IFERROR($I25^2*10000,0) -> 2474.6837
B26: =設定!B23 -> デュエル・マスターズ | C26: =SUMIFS(在庫管理!$O$11:$O$110,在庫管理!$L$11:$L$110,"在庫中",在庫管理!$C$11:$C$110,$B26) -> 0 | D26: =IFERROR($C26/$C$7,"") -> 0 | E26: =IFERROR($D26^2*10000,0) -> 0 | G26: IV(見送り) | H26: =SUMIFS(在庫管理!$O$11:$O$110,在庫管理!$L$11:$L$110,"在庫中",在庫管理!$V$11:$V$110,$G26) -> 0 | I26: =IFERROR($H26/$C$7,"") -> 0 | J26: =IFERROR($I26^2*10000,0) -> 0
B27: =設定!B24 -> マジック：ザ・ギャザリング | C27: =SUMIFS(在庫管理!$O$11:$O$110,在庫管理!$L$11:$L$110,"在庫中",在庫管理!$C$11:$C$110,$B27) -> 0 | D27: =IFERROR($C27/$C$7,"") -> 0 | E27: =IFERROR($D27^2*10000,0) -> 0 | G27: 合計 | H27: =SUM(H23:H26) -> 98500 | I27: =SUM(I23:I26) -> 1 | J27: =SUM(J23:J26) -> 3817.9288
B28: =設定!B25 -> その他 | C28: =SUMIFS(在庫管理!$O$11:$O$110,在庫管理!$L$11:$L$110,"在庫中",在庫管理!$C$11:$C$110,$B28) -> 0 | D28: =IFERROR($C28/$C$7,"") -> 0 | E28: =IFERROR($D28^2*10000,0) -> 0 | G28: 偏りの判定 | H28: =IF(J27>=2500,"偏りが大きい（要注意）",IF(J27>=1500,"中程度","分散（健全）")) -> 偏りが大きい（要注意）
B29: 合計 | C29: =SUM(C23:C28) -> 98500 | D29: =SUM(D23:D28) -> 1 | E29: =SUM(E23:E28) -> 3817.9288
B30: 偏りの判定 | C30: =IF(E29>=2500,"偏りが大きい（要注意）",IF(E29>=1500,"中程度","分散（健全）")) -> 偏りが大きい（要注意）
B32: キャラ | C32: 時価（在庫中） | D32: 構成比 | E32: 偏りスコア | G32: イラストレーター | H32: 時価（在庫中） | I32: 構成比 | J32: 偏りスコア
B33: =設定!B55 -> リザードン | C33: =IF($B33="","",SUMIFS(在庫管理!$O$11:$O$110,在庫管理!$L$11:$L$110,"在庫中",在庫管理!$D$11:$D$110,$B33)) -> 31000 | D33: =IFERROR($C33/$C$7,"") -> 0.31472081 | E33: =IFERROR($D33^2*10000,0) -> 990.4919 | G33: =設定!B78 -> サンプル絵師A | H33: =IF($G33="","",SUMIFS(在庫管理!$O$11:$O$110,在庫管理!$L$11:$L$110,"在庫中",在庫管理!$E$11:$E$110,$G33)) -> 31000 | I33: =IFERROR($H33/$C$7,"") -> 0.31472081 | J33: =IFERROR($I33^2*10000,0) -> 990.4919
B34: =設定!B56 -> ルフィ | C34: =IF($B34="","",SUMIFS(在庫管理!$O$11:$O$110,在庫管理!$L$11:$L$110,"在庫中",在庫管理!$D$11:$D$110,$B34)) -> 18500 | D34: =IFERROR($C34/$C$7,"") -> 0.18781726 | E34: =IFERROR($D34^2*10000,0) -> 352.75323 | G34: =設定!B79 -> サンプル絵師B | H34: =IF($G34="","",SUMIFS(在庫管理!$O$11:$O$110,在庫管理!$L$11:$L$110,"在庫中",在庫管理!$E$11:$E$110,$G34)) -> 0 | I34: =IFERROR($H34/$C$7,"") -> 0 | J34: =IFERROR($I34^2*10000,0) -> 0
B35: =設定!B57 -> 青眼の白龍 | C35: =IF($B35="","",SUMIFS(在庫管理!$O$11:$O$110,在庫管理!$L$11:$L$110,"在庫中",在庫管理!$D$11:$D$110,$B35)) -> 49000 | D35: =IFERROR($C35/$C$7,"") -> 0.49746193 | E35: =IFERROR($D35^2*10000,0) -> 2474.6837 | G35: =設定!B80 -> 0 | H35: =IF($G35="","",SUMIFS(在庫管理!$O$11:$O$110,在庫管理!$L$11:$L$110,"在庫中",在庫管理!$E$11:$E$110,$G35)) | I35: =IFERROR($H35/$C$7,"") | J35: =IFERROR($I35^2*10000,0) -> 0
B36: =設定!B58 -> 0 | C36: =IF($B36="","",SUMIFS(在庫管理!$O$11:$O$110,在庫管理!$L$11:$L$110,"在庫中",在庫管理!$D$11:$D$110,$B36)) | D36: =IFERROR($C36/$C$7,"") | E36: =IFERROR($D36^2*10000,0) -> 0 | G36: =設定!B81 -> 0 | H36: =IF($G36="","",SUMIFS(在庫管理!$O$11:$O$110,在庫管理!$L$11:$L$110,"在庫中",在庫管理!$E$11:$E$110,$G36)) | I36: =IFERROR($H36/$C$7,"") | J36: =IFERROR($I36^2*10000,0) -> 0
B37: =設定!B59 -> 0 | C37: =IF($B37="","",SUMIFS(在庫管理!$O$11:$O$110,在庫管理!$L$11:$L$110,"在庫中",在庫管理!$D$11:$D$110,$B37)) | D37: =IFERROR($C37/$C$7,"") | E37: =IFERROR($D37^2*10000,0) -> 0 | G37: =設定!B82 -> 0 | H37: =IF($G37="","",SUMIFS(在庫管理!$O$11:$O$110,在庫管理!$L$11:$L$110,"在庫中",在庫管理!$E$11:$E$110,$G37)) | I37: =IFERROR($H37/$C$7,"") | J37: =IFERROR($I37^2*10000,0) -> 0
B38: =設定!B60 -> 0 | C38: =IF($B38="","",SUMIFS(在庫管理!$O$11:$O$110,在庫管理!$L$11:$L$110,"在庫中",在庫管理!$D$11:$D$110,$B38)) | D38: =IFERROR($C38/$C$7,"") | E38: =IFERROR($D38^2*10000,0) -> 0 | G38: =設定!B83 -> 0 | H38: =IF($G38="","",SUMIFS(在庫管理!$O$11:$O$110,在庫管理!$L$11:$L$110,"在庫中",在庫管理!$E$11:$E$110,$G38)) | I38: =IFERROR($H38/$C$7,"") | J38: =IFERROR($I38^2*10000,0) -> 0
B39: =設定!B61 -> 0 | C39: =IF($B39="","",SUMIFS(在庫管理!$O$11:$O$110,在庫管理!$L$11:$L$110,"在庫中",在庫管理!$D$11:$D$110,$B39)) | D39: =IFERROR($C39/$C$7,"") | E39: =IFERROR($D39^2*10000,0) -> 0 | G39: =設定!B84 -> 0 | H39: =IF($G39="","",SUMIFS(在庫管理!$O$11:$O$110,在庫管理!$L$11:$L$110,"在庫中",在庫管理!$E$11:$E$110,$G39)) | I39: =IFERROR($H39/$C$7,"") | J39: =IFERROR($I39^2*10000,0) -> 0
B40: =設定!B62 -> 0 | C40: =IF($B40="","",SUMIFS(在庫管理!$O$11:$O$110,在庫管理!$L$11:$L$110,"在庫中",在庫管理!$D$11:$D$110,$B40)) | D40: =IFERROR($C40/$C$7,"") | E40: =IFERROR($D40^2*10000,0) -> 0 | G40: =設定!B85 -> 0 | H40: =IF($G40="","",SUMIFS(在庫管理!$O$11:$O$110,在庫管理!$L$11:$L$110,"在庫中",在庫管理!$E$11:$E$110,$G40)) | I40: =IFERROR($H40/$C$7,"") | J40: =IFERROR($I40^2*10000,0) -> 0
B41: =設定!B63 -> 0 | C41: =IF($B41="","",SUMIFS(在庫管理!$O$11:$O$110,在庫管理!$L$11:$L$110,"在庫中",在庫管理!$D$11:$D$110,$B41)) | D41: =IFERROR($C41/$C$7,"") | E41: =IFERROR($D41^2*10000,0) -> 0 | G41: =設定!B86 -> 0 | H41: =IF($G41="","",SUMIFS(在庫管理!$O$11:$O$110,在庫管理!$L$11:$L$110,"在庫中",在庫管理!$E$11:$E$110,$G41)) | I41: =IFERROR($H41/$C$7,"") | J41: =IFERROR($I41^2*10000,0) -> 0
B42: =設定!B64 -> 0 | C42: =IF($B42="","",SUMIFS(在庫管理!$O$11:$O$110,在庫管理!$L$11:$L$110,"在庫中",在庫管理!$D$11:$D$110,$B42)) | D42: =IFERROR($C42/$C$7,"") | E42: =IFERROR($D42^2*10000,0) -> 0 | G42: =設定!B87 -> 0 | H42: =IF($G42="","",SUMIFS(在庫管理!$O$11:$O$110,在庫管理!$L$11:$L$110,"在庫中",在庫管理!$E$11:$E$110,$G42)) | I42: =IFERROR($H42/$C$7,"") | J42: =IFERROR($I42^2*10000,0) -> 0
B43: =設定!B65 -> 0 | C43: =IF($B43="","",SUMIFS(在庫管理!$O$11:$O$110,在庫管理!$L$11:$L$110,"在庫中",在庫管理!$D$11:$D$110,$B43)) | D43: =IFERROR($C43/$C$7,"") | E43: =IFERROR($D43^2*10000,0) -> 0 | G43: =設定!B88 -> 0 | H43: =IF($G43="","",SUMIFS(在庫管理!$O$11:$O$110,在庫管理!$L$11:$L$110,"在庫中",在庫管理!$E$11:$E$110,$G43)) | I43: =IFERROR($H43/$C$7,"") | J43: =IFERROR($I43^2*10000,0) -> 0
B44: =設定!B66 -> 0 | C44: =IF($B44="","",SUMIFS(在庫管理!$O$11:$O$110,在庫管理!$L$11:$L$110,"在庫中",在庫管理!$D$11:$D$110,$B44)) | D44: =IFERROR($C44/$C$7,"") | E44: =IFERROR($D44^2*10000,0) -> 0 | G44: =設定!B89 -> 0 | H44: =IF($G44="","",SUMIFS(在庫管理!$O$11:$O$110,在庫管理!$L$11:$L$110,"在庫中",在庫管理!$E$11:$E$110,$G44)) | I44: =IFERROR($H44/$C$7,"") | J44: =IFERROR($I44^2*10000,0) -> 0
... B52: =設定!B74 -> 0 | C52: =IF($B52="","",SUMIFS(在庫管理!$O$11:$O$110,在庫管理!$L$11:$L$110,"在庫中",在庫管理!$D$11:$D$110,$B52)) | D52: =IFERROR($C52/$C$7,"") | E52: =IFERROR($D52^2*10000,0) -> 0 | G52: =設定!B97 -> 0 | H52: =IF($G52="","",SUMIFS(在庫管理!$O$11:$O$110,在庫管理!$L$11:$L$110,"在庫中",在庫管理!$E$11:$E$110,$G52)) | I52: =IFERROR($H52/$C$7,"") | J52: =IFERROR($I52^2*10000,0) -> 0
B53: その他（未登録キャラ／タグなし） | C53: =MAX(0,SUMIFS(在庫管理!$O$11:$O$110,在庫管理!$L$11:$L$110,"在庫中")-SUM(C33:C52)) -> 0 | D53: =IFERROR($C53/$C$7,"") -> 0 | E53: =IFERROR($D53^2*10000,0) -> 0 | G53: その他（未登録／タグなし） | H53: =MAX(0,SUMIFS(在庫管理!$O$11:$O$110,在庫管理!$L$11:$L$110,"在庫中")-SUM(H33:H52)) -> 67500 | I53: =IFERROR($H53/$C$7,"") -> 0.68527919 | J53: =IFERROR($I53^2*10000,0) -> 4696.0757
B54: 合計 | C54: =SUM(C33:C53) -> 98500 | D54: =SUM(D33:D53) -> 1 | E54: =SUM(E33:E53) -> 3817.9288 | G54: 合計 | H54: =SUM(H33:H53) -> 98500 | I54: =SUM(I33:I53) -> 1 | J54: =SUM(J33:J53) -> 5686.5675
B55: 偏りの判定 | C55: =IF(E54>=2500,"偏りが大きい（要注意）",IF(E54>=1500,"中程度","分散（健全）")) -> 偏りが大きい（要注意） | G55: 偏りの判定 | H55: =IF(J54>=2500,"偏りが大きい（要注意）",IF(J54>=1500,"中程度","分散（健全）")) -> 偏りが大きい（要注意）
B58: ■ 攻めと守りの評価（資本効率・実効流動性）
B59: 利益率×回転率＝「どれだけ稼ぐ力があるか」（攻めの評価・仕入れ優先順位の決定に使用）。流動性×ボラティリティ＝「いざという時に安全に現金化できるか」（守りの評価・ポジションサイズの抑制判断に使用）。
B60: 平均資本効率（利益率×回転率・時価加重） | C60: =IFERROR(SUMPRODUCT((在庫管理!$L$11:$L$110="在庫中")*N(在庫管理!$T$11:$T$110)*N(在庫管理!$O$11:$O$110))/$C$7,"") -> 3.7096413
B61: 平均実効想定売却日数（ボラティリティ考慮・時価加重） | C61: =IFERROR(SUMPRODUCT((在庫管理!$L$11:$L$110="在庫中")*N(在庫管理!$Q$11:$Q$110)*N(在庫管理!$O$11:$O$110))/$C$7,"") -> 35.729949
B63: ■ 象限別 枚数構成比（分布傾向のチェック）
B64: 時価ではなく点数（枚数）ベースの構成比。一般的には「コアが薄い層、回転（キャッシュ同等物）が最大ボリューム、厳選（グロース枠）が最少数・最高ボラ、見送り（劣後在庫）は低ボラで少量」という逆ピラミッド型になりやすい。
B65: 象限 | C65: 点数（在庫中） | D65: 構成比
B66: I(コア) | C66: =COUNTIFS(在庫管理!$L$11:$L$110,"在庫中",在庫管理!$V$11:$V$110,$B66) -> 1 | D66: =IFERROR($C66/$C$70,"") -> 0.33333333
B67: II(回転) | C67: =COUNTIFS(在庫管理!$L$11:$L$110,"在庫中",在庫管理!$V$11:$V$110,$B67) -> 1 | D67: =IFERROR($C67/$C$70,"") -> 0.33333333
B68: III(厳選) | C68: =COUNTIFS(在庫管理!$L$11:$L$110,"在庫中",在庫管理!$V$11:$V$110,$B68) -> 1 | D68: =IFERROR($C68/$C$70,"") -> 0.33333333
B69: IV(見送り) | C69: =COUNTIFS(在庫管理!$L$11:$L$110,"在庫中",在庫管理!$V$11:$V$110,$B69) -> 0 | D69: =IFERROR($C69/$C$70,"") -> 0
B70: 合計 | C70: =SUM(C66:C69) -> 3 | D70: =SUM(D66:D69) -> 1
B71: ■ 希少性帯別・企画別 偏りリスク（相関ドライバー：収録弾・レアリティ帯・企画単位の集中を確認）
B72: 希少性 | C72: 時価（在庫中） | D72: 構成比 | E72: 偏りスコア | G72: 企画・収録弾 | H72: 時価（在庫中） | I72: 構成比 | J72: 偏りスコア
B73: =設定!B29 -> SS | C73: =SUMIFS(在庫管理!$O$11:$O$110,在庫管理!$L$11:$L$110,"在庫中",在庫管理!$I$11:$I$110,$B73) -> 80000 | D73: =IFERROR($C73/$C$7,"") -> 0.81218274 | E73: =IFERROR($D73^2*10000,0) -> 6596.408 | G73: =設定!B102 -> スカーレット&バイオレット 151 | H73: =IF($G73="","",SUMIFS(在庫管理!$O$11:$O$110,在庫管理!$L$11:$L$110,"在庫中",在庫管理!$F$11:$F$110,$G73)) -> 31000 | I73: =IFERROR($H73/$C$7,"") -> 0.31472081 | J73: =IFERROR($I73^2*10000,0) -> 990.4919
B74: =設定!B30 -> S | C74: =SUMIFS(在庫管理!$O$11:$O$110,在庫管理!$L$11:$L$110,"在庫中",在庫管理!$I$11:$I$110,$B74) -> 18500 | D74: =IFERROR($C74/$C$7,"") -> 0.18781726 | E74: =IFERROR($D74^2*10000,0) -> 352.75323 | G74: =設定!B103 -> ROMANCE DAWN | H74: =IF($G74="","",SUMIFS(在庫管理!$O$11:$O$110,在庫管理!$L$11:$L$110,"在庫中",在庫管理!$F$11:$F$110,$G74)) -> 18500 | I74: =IFERROR($H74/$C$7,"") -> 0.18781726 | J74: =IFERROR($I74^2*10000,0) -> 352.75323
B75: =設定!B31 -> A | C75: =SUMIFS(在庫管理!$O$11:$O$110,在庫管理!$L$11:$L$110,"在庫中",在庫管理!$I$11:$I$110,$B75) -> 0 | D75: =IFERROR($C75/$C$7,"") -> 0 | E75: =IFERROR($D75^2*10000,0) -> 0 | G75: =設定!B104 -> 25周年記念 | H75: =IF($G75="","",SUMIFS(在庫管理!$O$11:$O$110,在庫管理!$L$11:$L$110,"在庫中",在庫管理!$F$11:$F$110,$G75)) -> 0 | I75: =IFERROR($H75/$C$7,"") -> 0 | J75: =IFERROR($I75^2*10000,0) -> 0
B76: =設定!B32 -> B | C76: =SUMIFS(在庫管理!$O$11:$O$110,在庫管理!$L$11:$L$110,"在庫中",在庫管理!$I$11:$I$110,$B76) -> 0 | D76: =IFERROR($C76/$C$7,"") -> 0 | E76: =IFERROR($D76^2*10000,0) -> 0 | G76: =設定!B105 -> 0 | H76: =IF($G76="","",SUMIFS(在庫管理!$O$11:$O$110,在庫管理!$L$11:$L$110,"在庫中",在庫管理!$F$11:$F$110,$G76)) | I76: =IFERROR($H76/$C$7,"") | J76: =IFERROR($I76^2*10000,0) -> 0
B77: =設定!B33 -> C | C77: =SUMIFS(在庫管理!$O$11:$O$110,在庫管理!$L$11:$L$110,"在庫中",在庫管理!$I$11:$I$110,$B77) -> 0 | D77: =IFERROR($C77/$C$7,"") -> 0 | E77: =IFERROR($D77^2*10000,0) -> 0 | G77: =設定!B106 -> 0 | H77: =IF($G77="","",SUMIFS(在庫管理!$O$11:$O$110,在庫管理!$L$11:$L$110,"在庫中",在庫管理!$F$11:$F$110,$G77)) | I77: =IFERROR($H77/$C$7,"") | J77: =IFERROR($I77^2*10000,0) -> 0
B78: 合計 | C78: =SUM(C73:C77) -> 98500 | D78: =SUM(D73:D77) -> 1 | E78: =SUM(E73:E77) -> 6949.1613 | G78: =設定!B107 -> 0 | H78: =IF($G78="","",SUMIFS(在庫管理!$O$11:$O$110,在庫管理!$L$11:$L$110,"在庫中",在庫管理!$F$11:$F$110,$G78)) | I78: =IFERROR($H78/$C$7,"") | J78: =IFERROR($I78^2*10000,0) -> 0
B79: 偏りの判定 | C79: =IF(E78>=2500,"偏りが大きい（要注意）",IF(E78>=1500,"中程度","分散（健全）")) -> 偏りが大きい（要注意） | G79: =設定!B108 -> 0 | H79: =IF($G79="","",SUMIFS(在庫管理!$O$11:$O$110,在庫管理!$L$11:$L$110,"在庫中",在庫管理!$F$11:$F$110,$G79)) | I79: =IFERROR($H79/$C$7,"") | J79: =IFERROR($I79^2*10000,0) -> 0
G80: =設定!B109 -> 0 | H80: =IF($G80="","",SUMIFS(在庫管理!$O$11:$O$110,在庫管理!$L$11:$L$110,"在庫中",在庫管理!$F$11:$F$110,$G80)) | I80: =IFERROR($H80/$C$7,"") | J80: =IFERROR($I80^2*10000,0) -> 0
G81: =設定!B110 -> 0 | H81: =IF($G81="","",SUMIFS(在庫管理!$O$11:$O$110,在庫管理!$L$11:$L$110,"在庫中",在庫管理!$F$11:$F$110,$G81)) | I81: =IFERROR($H81/$C$7,"") | J81: =IFERROR($I81^2*10000,0) -> 0
G82: =設定!B111 -> 0 | H82: =IF($G82="","",SUMIFS(在庫管理!$O$11:$O$110,在庫管理!$L$11:$L$110,"在庫中",在庫管理!$F$11:$F$110,$G82)) | I82: =IFERROR($H82/$C$7,"") | J82: =IFERROR($I82^2*10000,0) -> 0
G83: =設定!B112 -> 0 | H83: =IF($G83="","",SUMIFS(在庫管理!$O$11:$O$110,在庫管理!$L$11:$L$110,"在庫中",在庫管理!$F$11:$F$110,$G83)) | I83: =IFERROR($H83/$C$7,"") | J83: =IFERROR($I83^2*10000,0) -> 0
G84: =設定!B113 -> 0 | H84: =IF($G84="","",SUMIFS(在庫管理!$O$11:$O$110,在庫管理!$L$11:$L$110,"在庫中",在庫管理!$F$11:$F$110,$G84)) | I84: =IFERROR($H84/$C$7,"") | J84: =IFERROR($I84^2*10000,0) -> 0
G85: =設定!B114 -> 0 | H85: =IF($G85="","",SUMIFS(在庫管理!$O$11:$O$110,在庫管理!$L$11:$L$110,"在庫中",在庫管理!$F$11:$F$110,$G85)) | I85: =IFERROR($H85/$C$7,"") | J85: =IFERROR($I85^2*10000,0) -> 0
G86: =設定!B115 -> 0 | H86: =IF($G86="","",SUMIFS(在庫管理!$O$11:$O$110,在庫管理!$L$11:$L$110,"在庫中",在庫管理!$F$11:$F$110,$G86)) | I86: =IFERROR($H86/$C$7,"") | J86: =IFERROR($I86^2*10000,0) -> 0
G87: =設定!B116 -> 0 | H87: =IF($G87="","",SUMIFS(在庫管理!$O$11:$O$110,在庫管理!$L$11:$L$110,"在庫中",在庫管理!$F$11:$F$110,$G87)) | I87: =IFERROR($H87/$C$7,"") | J87: =IFERROR($I87^2*10000,0) -> 0
G88: =設定!B117 -> 0 | H88: =IF($G88="","",SUMIFS(在庫管理!$O$11:$O$110,在庫管理!$L$11:$L$110,"在庫中",在庫管理!$F$11:$F$110,$G88)) | I88: =IFERROR($H88/$C$7,"") | J88: =IFERROR($I88^2*10000,0) -> 0
G89: =設定!B118 -> 0 | H89: =IF($G89="","",SUMIFS(在庫管理!$O$11:$O$110,在庫管理!$L$11:$L$110,"在庫中",在庫管理!$F$11:$F$110,$G89)) | I89: =IFERROR($H89/$C$7,"") | J89: =IFERROR($I89^2*10000,0) -> 0
G90: =設定!B119 -> 0 | H90: =IF($G90="","",SUMIFS(在庫管理!$O$11:$O$110,在庫管理!$L$11:$L$110,"在庫中",在庫管理!$F$11:$F$110,$G90)) | I90: =IFERROR($H90/$C$7,"") | J90: =IFERROR($I90^2*10000,0) -> 0
G91: =設定!B120 -> 0 | H91: =IF($G91="","",SUMIFS(在庫管理!$O$11:$O$110,在庫管理!$L$11:$L$110,"在庫中",在庫管理!$F$11:$F$110,$G91)) | I91: =IFERROR($H91/$C$7,"") | J91: =IFERROR($I91^2*10000,0) -> 0
G92: =設定!B121 -> 0 | H92: =IF($G92="","",SUMIFS(在庫管理!$O$11:$O$110,在庫管理!$L$11:$L$110,"在庫中",在庫管理!$F$11:$F$110,$G92)) | I92: =IFERROR($H92/$C$7,"") | J92: =IFERROR($I92^2*10000,0) -> 0
G93: その他（未登録／タグなし） | H93: =MAX(0,SUMIFS(在庫管理!$O$11:$O$110,在庫管理!$L$11:$L$110,"在庫中")-SUM(H73:H92)) -> 49000 | I93: =IFERROR($H93/$C$7,"") -> 0.49746193 | J93: =IFERROR($I93^2*10000,0) -> 2474.6837
G94: 合計 | H94: =SUM(H73:H93) -> 98500 | I94: =SUM(I73:I93) -> 1 | J94: =SUM(J73:J93) -> 3817.9288
G95: 偏りの判定 | H95: =IF(J94>=2500,"偏りが大きい（要注意）",IF(J94>=1500,"中程度","分散（健全）")) -> 偏りが大きい（要注意）
